ICO_HW_Design/spi_slave_32bit.v
module SPI_Slave #(
    parameter [15:0] MAX_COUNT = 512  // Must be even
)(
    input  clk,
    input  SPI_CLK,
    input  SPI_PICO,
    input  SPI_CS,
    output SPI_POCI,
    input [15:0] pitch_data,
    input [15:0] yaw_data,
    input rst,
    output reg [15:0] pitch_pwm,
    output reg [15:0] yaw_pwm
);

    // this shouldn't be synthesizable, this is for test bench
    initial begin
        pitch_pwm = MAX_COUNT >> 1;
        yaw_pwm = MAX_COUNT >> 1;
        bitcnt = 5'b000;
        bytes_received = 1'b0;
        bytes_data_received = 32'd0;
        byte_data_sent = 32'd0;
    end

    reg [2:0] SPI_CLKr;
    always @(posedge clk) begin
        if (rst) begin
            SPI_CLKr <= 3'b000;
        end else begin
            SPI_CLKr <= {SPI_CLKr[1:0], SPI_CLK}; 
        end
    end

    wire SPI_CLK_risingedge = (SPI_CLKr[2:1] == 2'b01); 
    wire SPI_CLK_fallingedge = (SPI_CLKr[2:1] == 2'b10); 

    reg [2:0] SPI_CSr;
    always @(posedge clk) begin
        if (rst) begin
            SPI_CSr <= 3'b111;  // Assuming CS is inactive high, start with high state
        end else begin
            SPI_CSr <= {SPI_CSr[1:0], SPI_CS};
        end
    end

    wire SPI_CS_active = ~SPI_CSr[1];
    wire SPI_CS_startmessage = (SPI_CSr[2:1] == 2'b10);
    wire SPI_CS_endmessage = (SPI_CSr[2:1] == 2'b01);

    reg [1:0] SPI_PICOr;
    always @(posedge clk) begin
        if (rst) begin
            SPI_PICOr <= 2'b00;
        end else begin
            SPI_PICOr <= {SPI_PICOr[0], SPI_PICO};
        end
    end

    wire SPI_PICO_data = SPI_PICOr[1];

    reg [4:0] bitcnt; 
    reg bytes_received; 
    reg [31:0] bytes_data_received;

    always @(posedge clk) begin 
        if (rst) begin
            bitcnt <= 5'b000;
            bytes_data_received <= 32'd0;
        end else begin
            if (~SPI_CS_active) begin
                bitcnt <= 5'b000;
            end else if (SPI_CLK_risingedge) begin
                bitcnt <= bitcnt + 5'b001;
                bytes_data_received <= {bytes_data_received[30:0], SPI_PICO_data};
            end
        end
    end

    always @(posedge clk) begin
        if (rst) begin
            bytes_received <= 1'b0;
        end else begin
            bytes_received <= SPI_CS_active && SPI_CLK_risingedge && (bitcnt == 5'd31);
        end
    end

    always @(posedge clk) begin
        if (rst) begin
            pitch_pwm <= MAX_COUNT >> 1;
            yaw_pwm   <= MAX_COUNT >> 1;
        end else if (bytes_received) begin
           {pitch_pwm, yaw_pwm} <= bytes_data_received;
        end
    end

    reg [31:0] byte_data_sent;

    always @(posedge clk) begin
        if (rst) begin
            byte_data_sent <= 32'd0;
        end else if (SPI_CS_active) begin
            if (SPI_CS_startmessage) begin
                byte_data_sent <= {pitch_data, yaw_data};
            end else if (SPI_CLK_fallingedge) begin
                byte_data_sent <= {byte_data_sent[30:0], 1'b0};
            end
        end else begin
            byte_data_sent <= 32'd0;
        end
    end

    assign SPI_POCI = byte_data_sent[31];

endmodule

ICO_HW_Design/tb_spi_slave_32bit.v
`timescale 1ns / 1ps

module tb_SPI_Slave;

    // Parameters
    localparam CLK_PERIOD = 10;             // 100 MHz system clock
    localparam SPI_CLK_HALF_PERIOD = 50;    // 10 MHz SPI clock (half period for toggling)

    // DUT interface signals
    reg clk = 0;
    reg rst = 1;
    reg SPI_CLK = 0;
    reg SPI_PICO = 0;
    reg SPI_CS = 1;  // Active low
    wire SPI_POCI;
    reg [15:0] pitch_data = 16'hDEAD;
    reg [15:0] yaw_data   = 16'hBEEF;
    wire [15:0] pitch_pwm;
    wire [15:0] yaw_pwm;

    // Instantiate the Device Under Test (DUT)
    SPI_Slave uut (
        .clk(clk),
        .rst(rst),
        .SPI_CLK(SPI_CLK),
        .SPI_PICO(SPI_PICO),
        .SPI_CS(SPI_CS),
        .SPI_POCI(SPI_POCI),
        .pitch_data(pitch_data),
        .yaw_data(yaw_data),
        .pitch_pwm(pitch_pwm),
        .yaw_pwm(yaw_pwm)
    );

    // System clock generator
    always #(CLK_PERIOD / 2) clk = ~clk;

    // SPI full-duplex byte transfer
    task spi_transfer_byte(input [7:0] tx_byte, output [7:0] rx_byte);
        integer i;
        begin
            rx_byte = 8'h00;
            for (i = 7; i >= 0; i = i - 1) begin
                SPI_PICO = tx_byte[i];
                #(SPI_CLK_HALF_PERIOD);
                SPI_CLK = 1;
                rx_byte[i] = SPI_POCI;  // Sample on rising edge
                #(SPI_CLK_HALF_PERIOD);
                SPI_CLK = 0;
            end
        end
    endtask

    // SPI full-duplex 32-bit frame transfer (pitch + yaw)
    task spi_transfer_frame(input [31:0] tx_frame, output [31:0] rx_frame);
        reg [7:0] rx_b0, rx_b1, rx_b2, rx_b3;
        begin
            SPI_CS = 0;

            spi_transfer_byte(tx_frame[31:24], rx_b0);
            spi_transfer_byte(tx_frame[23:16], rx_b1);
            spi_transfer_byte(tx_frame[15:8],  rx_b2);
            spi_transfer_byte(tx_frame[7:0],   rx_b3);

            #(SPI_CLK_HALF_PERIOD * 2);
            SPI_CS = 1;

            rx_frame = {rx_b0, rx_b1, rx_b2, rx_b3};
        end
    endtask

    reg [31:0] tx_frame;
    reg [31:0] rx_frame;

    initial begin
        // VCD dump for waveform viewing
        $dumpfile("spi_slave_tb.vcd");
        $dumpvars(0, tb_SPI_Slave);

        // Reset sequence
        #(10 * CLK_PERIOD);
        rst = 0;

        // SPI frame to send: pitch = 0xBEEF, yaw = 0xDEAD
        #100;
        tx_frame = 32'hBEEFDEAD;

        spi_transfer_frame(tx_frame, rx_frame);

        // Wait and observe output
        #500;

        // Output results
        $display("Sent Frame     : 0x%h", tx_frame);
        $display("Received Frame : 0x%h", rx_frame);
        $display("pitch_pwm      : 0x%h", pitch_pwm);
        $display("yaw_pwm        : 0x%h", yaw_pwm);

        // Test verification
        if (pitch_pwm == 16'hBEEF && yaw_pwm == 16'hDEAD &&
            rx_frame[31:16] == pitch_data && rx_frame[15:0] == yaw_data) begin
            $display("Test PASSED.");
        end else begin
            $display("Test FAILED.");
        end

        #100;
        $finish;
    end

endmodule

ICO_HW_Design/spi_slave_tb.vcd
$date
	Fri Jul 25 18:58:21 2025
$end
$version
	Icarus Verilog
$end
$timescale
	1ps
$end
$scope module tb_SPI_Slave $end
$var wire 16 ! yaw_pwm [15:0] $end
$var wire 16 " pitch_pwm [15:0] $end
$var wire 1 # SPI_POCI $end
$var parameter 32 $ CLK_PERIOD $end
$var parameter 32 % SPI_CLK_HALF_PERIOD $end
$var reg 1 & SPI_CLK $end
$var reg 1 ' SPI_CS $end
$var reg 1 ( SPI_PICO $end
$var reg 1 ) clk $end
$var reg 16 * pitch_data [15:0] $end
$var reg 1 + rst $end
$var reg 32 , rx_frame [31:0] $end
$var reg 32 - tx_frame [31:0] $end
$var reg 16 . yaw_data [15:0] $end
$scope module uut $end
$var wire 1 & SPI_CLK $end
$var wire 1 ' SPI_CS $end
$var wire 1 / SPI_CS_active $end
$var wire 1 ( SPI_PICO $end
$var wire 1 ) clk $end
$var wire 16 0 pitch_data [15:0] $end
$var wire 1 + rst $end
$var wire 16 1 yaw_data [15:0] $end
$var wire 1 # SPI_POCI $end
$var wire 1 2 SPI_PICO_data $end
$var wire 1 3 SPI_CS_startmessage $end
$var wire 1 4 SPI_CS_endmessage $end
$var wire 1 5 SPI_CLK_risingedge $end
$var wire 1 6 SPI_CLK_fallingedge $end
$var parameter 16 7 MAX_COUNT $end
$var reg 3 8 SPI_CLKr [2:0] $end
$var reg 3 9 SPI_CSr [2:0] $end
$var reg 2 : SPI_PICOr [1:0] $end
$var reg 5 ; bitcnt [4:0] $end
$var reg 32 < byte_data_sent [31:0] $end
$var reg 32 = bytes_data_received [31:0] $end
$var reg 1 > bytes_received $end
$var reg 16 ? pitch_pwm [15:0] $end
$var reg 16 @ yaw_pwm [15:0] $end
$upscope $end
$scope task spi_transfer_byte $end
$var reg 8 A rx_byte [7:0] $end
$var reg 8 B tx_byte [7:0] $end
$var integer 32 C i [31:0] $end
$upscope $end
$scope task spi_transfer_frame $end
$var reg 8 D rx_b0 [7:0] $end
$var reg 8 E rx_b1 [7:0] $end
$var reg 8 F rx_b2 [7:0] $end
$var reg 8 G rx_b3 [7:0] $end
$var reg 32 H rx_frame [31:0] $end
$var reg 32 I tx_frame [31:0] $end
$upscope $end
$upscope $end
$enddefinitions $end
$comment Show the parameter values. $end
$dumpall
b1000000000 7
b110010 %
b1010 $
$end
#0
$dumpvars
bx I
bx H
bx G
bx F
bx E
bx D
bx C
bx B
bx A
b100000000 @
b100000000 ?
0>
b0 =
b0 <
b0 ;
bx :
bx 9
bx 8
x6
x5
x4
x3
x2
b1011111011101111 1
b1101111010101101 0
x/
b1011111011101111 .
bx -
bx ,
1+
b1101111010101101 *
0)
0(
1'
0&
0#
b100000000 "
b100000000 !
$end
#5000
0/
05
06
03
04
02
b0 8
b111 9
b0 :
1)
#10000
0)
#15000
1)
#20000
0)
#25000
1)
#30000
0)
#35000
1)
#40000
0)
#45000
1)
#50000
0)
#55000
1)
#60000
0)
#65000
1)
#70000
0)
#75000
1)
#80000
0)
#85000
1)
#90000
0)
#95000
1)
#100000
0)
0+
#105000
1)
#110000
0)
#115000
1)
#120000
0)
#125000
1)
#130000
0)
#135000
1)
#140000
0)
#145000
1)
#150000
0)
#155000
1)
#160000
0)
#165000
1)
#170000
0)
#175000
1)
#180000
0)
#185000
1)
#190000
0)
#195000
1)
#200000
0)
1(
b111 C
b0 A
b10111110 B
0'
b10111110111011111101111010101101 I
b10111110111011111101111010101101 -
#205000
b110 9
b1 :
1)
#210000
0)
#215000
1/
12
13
b11 :
b100 9
1)
#220000
0)
#225000
03
1#
b0 9
b11011110101011011011111011101111 <
1)
#230000
0)
#235000
1)
#240000
0)
#245000
1)
#250000
0)
b10000000 A
1&
#255000
b1 8
1)
#260000
0)
#265000
15
b11 8
1)
#270000
0)
#275000
05
b1 =
b1 ;
b111 8
1)
#280000
0)
#285000
1)
#290000
0)
#295000
1)
#300000
0)
0(
b110 C
0&
#305000
b110 8
b10 :
1)
#310000
0)
#315000
02
16
b0 :
b100 8
1)
#320000
0)
#325000
06
b0 8
b10111101010110110111110111011110 <
1)
#330000
0)
#335000
1)
#340000
0)
#345000
1)
#350000
0)
b11000000 A
1&
#355000
b1 8
1)
#360000
0)
#365000
15
b11 8
1)
#370000
0)
#375000
05
b10 =
b10 ;
b111 8
1)
#380000
0)
#385000
1)
#390000
0)
#395000
1)
#400000
0)
1(
b101 C
0&
#405000
b110 8
b1 :
1)
#410000
0)
#415000
12
16
b11 :
b100 8
1)
#420000
0)
#425000
06
0#
b0 8
b1111010101101101111101110111100 <
1)
#430000
0)
#435000
1)
#440000
0)
#445000
1)
#450000
0)
1&
#455000
b1 8
1)
#460000
0)
#465000
15
b11 8
1)
#470000
0)
#475000
05
b101 =
b11 ;
b111 8
1)
#480000
0)
#485000
1)
#490000
0)
#495000
1)
#500000
0)
b100 C
0&
#505000
b110 8
1)
#510000
0)
#515000
16
b100 8
1)
#520000
0)
#525000
06
1#
b0 8
b11110101011011011111011101111000 <
1)
#530000
0)
#535000
1)
#540000
0)
#545000
1)
#550000
0)
b11010000 A
1&
#555000
b1 8
1)
#560000
0)
#565000
15
b11 8
1)
#570000
0)
#575000
05
b1011 =
b100 ;
b111 8
1)
#580000
0)
#585000
1)
#590000
0)
#595000
1)
#600000
0)
b11 C
0&
#605000
b110 8
1)
#610000
0)
#615000
16
b100 8
1)
#620000
0)
#625000
06
b0 8
b11101010110110111110111011110000 <
1)
#630000
0)
#635000
1)
#640000
0)
#645000
1)
#650000
0)
b11011000 A
1&
#655000
b1 8
1)
#660000
0)
#665000
15
b11 8
1)
#670000
0)
#675000
05
b10111 =
b101 ;
b111 8
1)
#680000
0)
#685000
1)
#690000
0)
#695000
1)
#700000
0)
b10 C
0&
#705000
b110 8
1)
#710000
0)
#715000
16
b100 8
1)
#720000
0)
#725000
06
b0 8
b11010101101101111101110111100000 <
1)
#730000
0)
#735000
1)
#740000
0)
#745000
1)
#750000
0)
b11011100 A
1&
#755000
b1 8
1)
#760000
0)
#765000
15
b11 8
1)
#770000
0)
#775000
05
b101111 =
b110 ;
b111 8
1)
#780000
0)
#785000
1)
#790000
0)
#795000
1)
#800000
0)
b1 C
0&
#805000
b110 8
1)
#810000
0)
#815000
16
b100 8
1)
#820000
0)
#825000
06
b0 8
b10101011011011111011101111000000 <
1)
#830000
0)
#835000
1)
#840000
0)
#845000
1)
#850000
0)
b11011110 A
1&
#855000
b1 8
1)
#860000
0)
#865000
15
b11 8
1)
#870000
0)
#875000
05
b1011111 =
b111 ;
b111 8
1)
#880000
0)
#885000
1)
#890000
0)
#895000
1)
#900000
0)
0(
b0 C
0&
#905000
b110 8
b10 :
1)
#910000
0)
#915000
02
16
b0 :
b100 8
1)
#920000
0)
#925000
06
0#
b0 8
b1010110110111110111011110000000 <
1)
#930000
0)
#935000
1)
#940000
0)
#945000
1)
#950000
0)
1&
#955000
b1 8
1)
#960000
0)
#965000
15
b11 8
1)
#970000
0)
#975000
05
b10111110 =
b1000 ;
b111 8
1)
#980000
0)
#985000
1)
#990000
0)
#995000
1)
#1000000
0)
1(
b0 A
b11101111 B
b11011110 D
b111 C
0&
#1005000
b110 8
b1 :
1)
#1010000
0)
#1015000
12
16
b11 :
b100 8
1)
#1020000
0)
#1025000
06
1#
b0 8
b10101101101111101110111100000000 <
1)
#1030000
0)
#1035000
1)
#1040000
0)
#1045000
1)
#1050000
0)
b10000000 A
1&
#1055000
b1 8
1)
#1060000
0)
#1065000
15
b11 8
1)
#1070000
0)
#1075000
05
b101111101 =
b1001 ;
b111 8
1)
#1080000
0)
#1085000
1)
#1090000
0)
#1095000
1)
#1100000
0)
b110 C
0&
#1105000
b110 8
1)
#1110000
0)
#1115000
16
b100 8
1)
#1120000
0)
#1125000
06
0#
b0 8
b1011011011111011101111000000000 <
1)
#1130000
0)
#1135000
1)
#1140000
0)
#1145000
1)
#1150000
0)
1&
#1155000
b1 8
1)
#1160000
0)
#1165000
15
b11 8
1)
#1170000
0)
#1175000
05
b1011111011 =
b1010 ;
b111 8
1)
#1180000
0)
#1185000
1)
#1190000
0)
#1195000
1)
#1200000
0)
b101 C
0&
#1205000
b110 8
1)
#1210000
0)
#1215000
16
b100 8
1)
#1220000
0)
#1225000
06
1#
b0 8
b10110110111110111011110000000000 <
1)
#1230000
0)
#1235000
1)
#1240000
0)
#1245000
1)
#1250000
0)
b10100000 A
1&
#1255000
b1 8
1)
#1260000
0)
#1265000
15
b11 8
1)
#1270000
0)
#1275000
05
b10111110111 =
b1011 ;
b111 8
1)
#1280000
0)
#1285000
1)
#1290000
0)
#1295000
1)
#1300000
0)
0(
b100 C
0&
#1305000
b110 8
b10 :
1)
#1310000
0)
#1315000
02
16
b0 :
b100 8
1)
#1320000
0)
#1325000
06
0#
b0 8
b1101101111101110111100000000000 <
1)
#1330000
0)
#1335000
1)
#1340000
0)
#1345000
1)
#1350000
0)
1&
#1355000
b1 8
1)
#1360000
0)
#1365000
15
b11 8
1)
#1370000
0)
#1375000
05
b101111101110 =
b1100 ;
b111 8
1)
#1380000
0)
#1385000
1)
#1390000
0)
#1395000
1)
#1400000
0)
1(
b11 C
0&
#1405000
b110 8
b1 :
1)
#1410000
0)
#1415000
12
16
b11 :
b100 8
1)
#1420000
0)
#1425000
06
1#
b0 8
b11011011111011101111000000000000 <
1)
#1430000
0)
#1435000
1)
#1440000
0)
#1445000
1)
#1450000
0)
b10101000 A
1&
#1455000
b1 8
1)
#1460000
0)
#1465000
15
b11 8
1)
#1470000
0)
#1475000
05
b1011111011101 =
b1101 ;
b111 8
1)
#1480000
0)
#1485000
1)
#1490000
0)
#1495000
1)
#1500000
0)
b10 C
0&
#1505000
b110 8
1)
#1510000
0)
#1515000
16
b100 8
1)
#1520000
0)
#1525000
06
b0 8
b10110111110111011110000000000000 <
1)
#1530000
0)
#1535000
1)
#1540000
0)
#1545000
1)
#1550000
0)
b10101100 A
1&
#1555000
b1 8
1)
#1560000
0)
#1565000
15
b11 8
1)
#1570000
0)
#1575000
05
b10111110111011 =
b1110 ;
b111 8
1)
#1580000
0)
#1585000
1)
#1590000
0)
#1595000
1)
#1600000
0)
b1 C
0&
#1605000
b110 8
1)
#1610000
0)
#1615000
16
b100 8
1)
#1620000
0)
#1625000
06
0#
b0 8
b1101111101110111100000000000000 <
1)
#1630000
0)
#1635000
1)
#1640000
0)
#1645000
1)
#1650000
0)
1&
#1655000
b1 8
1)
#1660000
0)
#1665000
15
b11 8
1)
#1670000
0)
#1675000
05
b101111101110111 =
b1111 ;
b111 8
1)
#1680000
0)
#1685000
1)
#1690000
0)
#1695000
1)
#1700000
0)
b0 C
0&
#1705000
b110 8
1)
#1710000
0)
#1715000
16
b100 8
1)
#1720000
0)
#1725000
06
1#
b0 8
b11011111011101111000000000000000 <
1)
#1730000
0)
#1735000
1)
#1740000
0)
#1745000
1)
#1750000
0)
b10101101 A
1&
#1755000
b1 8
1)
#1760000
0)
#1765000
15
b11 8
1)
#1770000
0)
#1775000
05
b1011111011101111 =
b10000 ;
b111 8
1)
#1780000
0)
#1785000
1)
#1790000
0)
#1795000
1)
#1800000
0)
b0 A
b11011110 B
b10101101 E
b111 C
0&
#1805000
b110 8
1)
#1810000
0)
#1815000
16
b100 8
1)
#1820000
0)
#1825000
06
b0 8
b10111110111011110000000000000000 <
1)
#1830000
0)
#1835000
1)
#1840000
0)
#1845000
1)
#1850000
0)
b10000000 A
1&
#1855000
b1 8
1)
#1860000
0)
#1865000
15
b11 8
1)
#1870000
0)
#1875000
05
b10111110111011111 =
b10001 ;
b111 8
1)
#1880000
0)
#1885000
1)
#1890000
0)
#1895000
1)
#1900000
0)
b110 C
0&
#1905000
b110 8
1)
#1910000
0)
#1915000
16
b100 8
1)
#1920000
0)
#1925000
06
0#
b0 8
b1111101110111100000000000000000 <
1)
#1930000
0)
#1935000
1)
#1940000
0)
#1945000
1)
#1950000
0)
1&
#1955000
b1 8
1)
#1960000
0)
#1965000
15
b11 8
1)
#1970000
0)
#1975000
05
b101111101110111111 =
b10010 ;
b111 8
1)
#1980000
0)
#1985000
1)
#1990000
0)
#1995000
1)
#2000000
0)
0(
b101 C
0&
#2005000
b110 8
b10 :
1)
#2010000
0)
#2015000
02
16
b0 :
b100 8
1)
#2020000
0)
#2025000
06
1#
b0 8
b11111011101111000000000000000000 <
1)
#2030000
0)
#2035000
1)
#2040000
0)
#2045000
1)
#2050000
0)
b10100000 A
1&
#2055000
b1 8
1)
#2060000
0)
#2065000
15
b11 8
1)
#2070000
0)
#2075000
05
b1011111011101111110 =
b10011 ;
b111 8
1)
#2080000
0)
#2085000
1)
#2090000
0)
#2095000
1)
#2100000
0)
1(
b100 C
0&
#2105000
b110 8
b1 :
1)
#2110000
0)
#2115000
12
16
b11 :
b100 8
1)
#2120000
0)
#2125000
06
b0 8
b11110111011110000000000000000000 <
1)
#2130000
0)
#2135000
1)
#2140000
0)
#2145000
1)
#2150000
0)
b10110000 A
1&
#2155000
b1 8
1)
#2160000
0)
#2165000
15
b11 8
1)
#2170000
0)
#2175000
05
b10111110111011111101 =
b10100 ;
b111 8
1)
#2180000
0)
#2185000
1)
#2190000
0)
#2195000
1)
#2200000
0)
b11 C
0&
#2205000
b110 8
1)
#2210000
0)
#2215000
16
b100 8
1)
#2220000
0)
#2225000
06
b0 8
b11101110111100000000000000000000 <
1)
#2230000
0)
#2235000
1)
#2240000
0)
#2245000
1)
#2250000
0)
b10111000 A
1&
#2255000
b1 8
1)
#2260000
0)
#2265000
15
b11 8
1)
#2270000
0)
#2275000
05
b101111101110111111011 =
b10101 ;
b111 8
1)
#2280000
0)
#2285000
1)
#2290000
0)
#2295000
1)
#2300000
0)
b10 C
0&
#2305000
b110 8
1)
#2310000
0)
#2315000
16
b100 8
1)
#2320000
0)
#2325000
06
b0 8
b11011101111000000000000000000000 <
1)
#2330000
0)
#2335000
1)
#2340000
0)
#2345000
1)
#2350000
0)
b10111100 A
1&
#2355000
b1 8
1)
#2360000
0)
#2365000
15
b11 8
1)
#2370000
0)
#2375000
05
b1011111011101111110111 =
b10110 ;
b111 8
1)
#2380000
0)
#2385000
1)
#2390000
0)
#2395000
1)
#2400000
0)
b1 C
0&
#2405000
b110 8
1)
#2410000
0)
#2415000
16
b100 8
1)
#2420000
0)
#2425000
06
b0 8
b10111011110000000000000000000000 <
1)
#2430000
0)
#2435000
1)
#2440000
0)
#2445000
1)
#2450000
0)
b10111110 A
1&
#2455000
b1 8
1)
#2460000
0)
#2465000
15
b11 8
1)
#2470000
0)
#2475000
05
b10111110111011111101111 =
b10111 ;
b111 8
1)
#2480000
0)
#2485000
1)
#2490000
0)
#2495000
1)
#2500000
0)
0(
b0 C
0&
#2505000
b110 8
b10 :
1)
#2510000
0)
#2515000
02
16
b0 :
b100 8
1)
#2520000
0)
#2525000
06
0#
b0 8
b1110111100000000000000000000000 <
1)
#2530000
0)
#2535000
1)
#2540000
0)
#2545000
1)
#2550000
0)
1&
#2555000
b1 8
1)
#2560000
0)
#2565000
15
b11 8
1)
#2570000
0)
#2575000
05
b101111101110111111011110 =
b11000 ;
b111 8
1)
#2580000
0)
#2585000
1)
#2590000
0)
#2595000
1)
#2600000
0)
1(
b0 A
b10101101 B
b10111110 F
b111 C
0&
#2605000
b110 8
b1 :
1)
#2610000
0)
#2615000
12
16
b11 :
b100 8
1)
#2620000
0)
#2625000
06
1#
b0 8
b11101111000000000000000000000000 <
1)
#2630000
0)
#2635000
1)
#2640000
0)
#2645000
1)
#2650000
0)
b10000000 A
1&
#2655000
b1 8
1)
#2660000
0)
#2665000
15
b11 8
1)
#2670000
0)
#2675000
05
b1011111011101111110111101 =
b11001 ;
b111 8
1)
#2680000
0)
#2685000
1)
#2690000
0)
#2695000
1)
#2700000
0)
0(
b110 C
0&
#2705000
b110 8
b10 :
1)
#2710000
0)
#2715000
02
16
b0 :
b100 8
1)
#2720000
0)
#2725000
06
b0 8
b11011110000000000000000000000000 <
1)
#2730000
0)
#2735000
1)
#2740000
0)
#2745000
1)
#2750000
0)
b11000000 A
1&
#2755000
b1 8
1)
#2760000
0)
#2765000
15
b11 8
1)
#2770000
0)
#2775000
05
b10111110111011111101111010 =
b11010 ;
b111 8
1)
#2780000
0)
#2785000
1)
#2790000
0)
#2795000
1)
#2800000
0)
1(
b101 C
0&
#2805000
b110 8
b1 :
1)
#2810000
0)
#2815000
12
16
b11 :
b100 8
1)
#2820000
0)
#2825000
06
b0 8
b10111100000000000000000000000000 <
1)
#2830000
0)
#2835000
1)
#2840000
0)
#2845000
1)
#2850000
0)
b11100000 A
1&
#2855000
b1 8
1)
#2860000
0)
#2865000
15
b11 8
1)
#2870000
0)
#2875000
05
b101111101110111111011110101 =
b11011 ;
b111 8
1)
#2880000
0)
#2885000
1)
#2890000
0)
#2895000
1)
#2900000
0)
0(
b100 C
0&
#2905000
b110 8
b10 :
1)
#2910000
0)
#2915000
02
16
b0 :
b100 8
1)
#2920000
0)
#2925000
06
0#
b0 8
b1111000000000000000000000000000 <
1)
#2930000
0)
#2935000
1)
#2940000
0)
#2945000
1)
#2950000
0)
1&
#2955000
b1 8
1)
#2960000
0)
#2965000
15
b11 8
1)
#2970000
0)
#2975000
05
b1011111011101111110111101010 =
b11100 ;
b111 8
1)
#2980000
0)
#2985000
1)
#2990000
0)
#2995000
1)
#3000000
0)
1(
b11 C
0&
#3005000
b110 8
b1 :
1)
#3010000
0)
#3015000
12
16
b11 :
b100 8
1)
#3020000
0)
#3025000
06
1#
b0 8
b11110000000000000000000000000000 <
1)
#3030000
0)
#3035000
1)
#3040000
0)
#3045000
1)
#3050000
0)
b11101000 A
1&
#3055000
b1 8
1)
#3060000
0)
#3065000
15
b11 8
1)
#3070000
0)
#3075000
05
b10111110111011111101111010101 =
b11101 ;
b111 8
1)
#3080000
0)
#3085000
1)
#3090000
0)
#3095000
1)
#3100000
0)
b10 C
0&
#3105000
b110 8
1)
#3110000
0)
#3115000
16
b100 8
1)
#3120000
0)
#3125000
06
b0 8
b11100000000000000000000000000000 <
1)
#3130000
0)
#3135000
1)
#3140000
0)
#3145000
1)
#3150000
0)
b11101100 A
1&
#3155000
b1 8
1)
#3160000
0)
#3165000
15
b11 8
1)
#3170000
0)
#3175000
05
b101111101110111111011110101011 =
b11110 ;
b111 8
1)
#3180000
0)
#3185000
1)
#3190000
0)
#3195000
1)
#3200000
0)
0(
b1 C
0&
#3205000
b110 8
b10 :
1)
#3210000
0)
#3215000
02
16
b0 :
b100 8
1)
#3220000
0)
#3225000
06
b0 8
b11000000000000000000000000000000 <
1)
#3230000
0)
#3235000
1)
#3240000
0)
#3245000
1)
#3250000
0)
b11101110 A
1&
#3255000
b1 8
1)
#3260000
0)
#3265000
15
b11 8
1)
#3270000
0)
#3275000
05
b1011111011101111110111101010110 =
b11111 ;
b111 8
1)
#3280000
0)
#3285000
1)
#3290000
0)
#3295000
1)
#3300000
0)
1(
b0 C
0&
#3305000
b110 8
b1 :
1)
#3310000
0)
#3315000
12
16
b11 :
b100 8
1)
#3320000
0)
#3325000
06
b0 8
b10000000000000000000000000000000 <
1)
#3330000
0)
#3335000
1)
#3340000
0)
#3345000
1)
#3350000
0)
b11101111 A
1&
#3355000
b1 8
1)
#3360000
0)
#3365000
15
b11 8
1)
#3370000
0)
#3375000
05
1>
b10111110111011111101111010101101 =
b0 ;
b111 8
1)
#3380000
0)
#3385000
0>
b1011111011101111 "
b1011111011101111 ?
b1101111010101101 !
b1101111010101101 @
1)
#3390000
0)
#3395000
1)
#3400000
0)
b11101111 G
b11111111111111111111111111111111 C
0&
#3405000
b110 8
1)
#3410000
0)
#3415000
16
b100 8
1)
#3420000
0)
#3425000
06
0#
b0 8
b0 <
1)
#3430000
0)
#3435000
1)
#3440000
0)
#3445000
1)
#3450000
0)
#3455000
1)
#3460000
0)
#3465000
1)
#3470000
0)
#3475000
1)
#3480000
0)
#3485000
1)
#3490000
0)
#3495000
1)
#3500000
0)
b11011110101011011011111011101111 ,
b11011110101011011011111011101111 H
1'
#3505000
b1 9
1)
#3510000
0)
#3515000
0/
14
b11 9
1)
#3520000
0)
#3525000
04
b111 9
1)
