Unselected Hardware/triangular_pwm.v
module triangular_pwm #(
    parameter DUTY_WIDTH = 8  // Also sets counter resolution
)(
    input  wire                   clk,
    input  wire                   rst,
    input  wire [DUTY_WIDTH-1:0]  duty,
    output reg                    pwm_out
);
    reg [DUTY_WIDTH-1:0] local_duty;
    always @(posedge clk) begin
        if (rst) begin
            local_duty <=0;
        end else if(counter == 0) begin
            local_duty <= duty;
        end

    end
    // Internal triangular counter
    reg [DUTY_WIDTH-1:0] counter;
    reg direction;  // 0 = up, 1 = down

    wire [DUTY_WIDTH-1:0] max_val = (1 << DUTY_WIDTH) - 1;

    // --- Counter logic (triangle waveform) ---
    always @(posedge clk) begin
        if (rst) begin
            counter   <= 0;
            direction <= 0;
        end else begin
            if (!direction) begin
                if (counter == max_val) begin
                    direction <= 1;
                    counter <= counter - 1;
                end else begin
                    counter <= counter + 1;
                end
            end else begin
                if (counter == 0) begin
                    direction <= 0;
                    counter <= counter + 1;
                end else begin
                    counter <= counter - 1;
                end
            end
        end
    end

    // --- PWM Output ---
    always @(posedge clk) begin
        if (rst) begin
            pwm_out <= 0;
        end else if (local_duty == 0) begin
            pwm_out <= 0;  // Special case: 0% local_duty
        end else if (local_duty == max_val) begin
            pwm_out <= 1;  // Special case: 100% local_duty
        end else begin
            pwm_out <= (counter < local_duty);
        end
    end

endmodule

Unselected Hardware/edge_pwm.v
module edge_pwm #(
    parameter DUTY_WIDTH = 8
)(
    input  wire                   clk,
    input  wire                   rst,
    input  wire [DUTY_WIDTH-1:0]  duty,
    output reg                    pwm_out
);

    reg [DUTY_WIDTH-1:0] counter;

    reg [DUTY_WIDTH-1:0] local_duty;
    always @(posedge clk) begin
        if (rst) begin
            local_duty <=0;
        end else if(counter == 0) begin
            local_duty <= duty;
        end

    end

    wire [DUTY_WIDTH-1:0] max_val = (1 << DUTY_WIDTH) - 1;

    // --- Counter logic ---
    always @(posedge clk) begin
        if (rst)
            counter <= 0;
        else
            counter <= (counter == max_val) ? 0 : counter + 1;
    end

    // --- PWM output logic with edge-aligned style ---
    always @(posedge clk) begin
        if (rst)
            pwm_out <= 0;
        else if (local_duty == 0)
            pwm_out <= 0;
        else if (local_duty == max_val)
            pwm_out <= 1;
        else
            pwm_out <= (counter < local_duty);
    end

endmodule

Unselected Hardware/tb_compare_pwm.v
`timescale 1ns / 1ps

module tb_compare_pwm;

    localparam DUTY_WIDTH = 8;
    localparam CLK_PERIOD = 10;

    reg clk = 0;
    reg rst;
    reg [DUTY_WIDTH-1:0] duty;

    wire pwm_edge;
    wire pwm_tri;

    // Instantiate edge-aligned PWM
    edge_pwm #(
        .DUTY_WIDTH(DUTY_WIDTH)
    ) edge_inst (
        .clk(clk),
        .rst(rst),
        .duty(duty),
        .pwm_out(pwm_edge)
    );

    // Instantiate triangular (center-aligned) PWM
    triangular_pwm #(
        .DUTY_WIDTH(7)
    ) tri_inst (
        .clk(clk),
        .rst(rst),
        .duty(duty>>1),
        .pwm_out(pwm_tri)
    );

    // Clock generation
    always #(CLK_PERIOD / 2) clk = ~clk;

    initial begin
        $dumpfile("compare_pwm.vcd");
        $dumpvars(0, tb_compare_pwm);

        rst = 1;
        duty = 0;
        #(5 * CLK_PERIOD);
        rst = 0;

        // Sweep through a few duty settings
        duty = 0;  #(3000 * CLK_PERIOD);
        duty = 8;  #(3000 * CLK_PERIOD);
        duty = 16;  #(3000 * CLK_PERIOD);
        duty = 32;  #(3000 * CLK_PERIOD);
        duty = 64;  #(3000 * CLK_PERIOD);
        duty = 128; #(3000 * CLK_PERIOD);
        duty = 192; #(3000 * CLK_PERIOD);
        duty = 255; #(3000 * CLK_PERIOD);

        $finish;
    end

endmodule

Unselected Hardware/compare_pwm.vcd
$date
	Tue Jul 29 17:37:59 2025
$end
$version
	Icarus Verilog
$end
$timescale
	1ps
$end
$scope module tb_compare_pwm $end
$var wire 1 ! pwm_tri $end
$var wire 1 " pwm_edge $end
$var parameter 32 # CLK_PERIOD $end
$var parameter 32 $ DUTY_WIDTH $end
$var reg 1 % clk $end
$var reg 8 & duty [7:0] $end
$var reg 1 ' rst $end
$scope module edge_inst $end
$var wire 1 % clk $end
$var wire 8 ( duty [7:0] $end
$var wire 8 ) max_val [7:0] $end
$var wire 1 ' rst $end
$var parameter 32 * DUTY_WIDTH $end
$var reg 8 + counter [7:0] $end
$var reg 8 , local_duty [7:0] $end
$var reg 1 " pwm_out $end
$upscope $end
$scope module tri_inst $end
$var wire 1 % clk $end
$var wire 7 - duty [6:0] $end
$var wire 7 . max_val [6:0] $end
$var wire 1 ' rst $end
$var parameter 32 / DUTY_WIDTH $end
$var reg 7 0 counter [6:0] $end
$var reg 1 1 direction $end
$var reg 7 2 local_duty [6:0] $end
$var reg 1 ! pwm_out $end
$upscope $end
$upscope $end
$enddefinitions $end
$comment Show the parameter values. $end
$dumpall
b111 /
b1000 *
b1000 $
b1010 #
$end
#0
$dumpvars
bx 2
x1
bx 0
b1111111 .
b0 -
bx ,
bx +
b11111111 )
b0 (
1'
b0 &
0%
x"
x!
$end
#5000
b0 ,
b0 +
0"
b0 2
01
b0 0
0!
1%
#10000
0%
#15000
1%
#20000
0%
#25000
1%
#30000
0%
#35000
1%
#40000
0%
#45000
1%
#50000
0%
0'
#55000
b1 0
b1 +
1%
#60000
0%
#65000
b10 +
b10 0
1%
#70000
0%
#75000
b11 0
b11 +
1%
#80000
0%
#85000
b100 +
b100 0
1%
#90000
0%
#95000
b101 0
b101 +
1%
#100000
0%
#105000
b110 +
b110 0
1%
#110000
0%
#115000
b111 0
b111 +
1%
#120000
0%
#125000
b1000 +
b1000 0
1%
#130000
0%
#135000
b1001 0
b1001 +
1%
#140000
0%
#145000
b1010 +
b1010 0
1%
#150000
0%
#155000
b1011 0
b1011 +
1%
#160000
0%
#165000
b1100 +
b1100 0
1%
#170000
0%
#175000
b1101 0
b1101 +
1%
#180000
0%
#185000
b1110 +
b1110 0
1%
#190000
0%
#195000
b1111 0
b1111 +
1%
#200000
0%
#205000
b10000 +
b10000 0
1%
#210000
0%
#215000
b10001 0
b10001 +
1%
#220000
0%
#225000
b10010 +
b10010 0
1%
#230000
0%
#235000
b10011 0
b10011 +
1%
#240000
0%
#245000
b10100 +
b10100 0
1%
#250000
0%
#255000
b10101 0
b10101 +
1%
#260000
0%
#265000
b10110 +
b10110 0
1%
#270000
0%
#275000
b10111 0
b10111 +
1%
#280000
0%
#285000
b11000 +
b11000 0
1%
#290000
0%
#295000
b11001 0
b11001 +
1%
#300000
0%
#305000
b11010 +
b11010 0
1%
#310000
0%
#315000
b11011 0
b11011 +
1%
#320000
0%
#325000
b11100 +
b11100 0
1%
#330000
0%
#335000
b11101 0
b11101 +
1%
#340000
0%
#345000
b11110 +
b11110 0
1%
#350000
0%
#355000
b11111 0
b11111 +
1%
#360000
0%
#365000
b100000 +
b100000 0
1%
#370000
0%
#375000
b100001 0
b100001 +
1%
#380000
0%
#385000
b100010 +
b100010 0
1%
#390000
0%
#395000
b100011 0
b100011 +
1%
#400000
0%
#405000
b100100 +
b100100 0
1%
#410000
0%
#415000
b100101 0
b100101 +
1%
#420000
0%
#425000
b100110 +
b100110 0
1%
#430000
0%
#435000
b100111 0
b100111 +
1%
#440000
0%
#445000
b101000 +
b101000 0
1%
#450000
0%
#455000
b101001 0
b101001 +
1%
#460000
0%
#465000
b101010 +
b101010 0
1%
#470000
0%
#475000
b101011 0
b101011 +
1%
#480000
0%
#485000
b101100 +
b101100 0
1%
#490000
0%
#495000
b101101 0
b101101 +
1%
#500000
0%
#505000
b101110 +
b101110 0
1%
#510000
0%
#515000
b101111 0
b101111 +
1%
#520000
0%
#525000
b110000 +
b110000 0
1%
#530000
0%
#535000
b110001 0
b110001 +
1%
#540000
0%
#545000
b110010 +
b110010 0
1%
#550000
0%
#555000
b110011 0
b110011 +
1%
#560000
0%
#565000
b110100 +
b110100 0
1%
#570000
0%
#575000
b110101 0
b110101 +
1%
#580000
0%
#585000
b110110 +
b110110 0
1%
#590000
0%
#595000
b110111 0
b110111 +
1%
#600000
0%
#605000
b111000 +
b111000 0
1%
#610000
0%
#615000
b111001 0
b111001 +
1%
#620000
0%
#625000
b111010 +
b111010 0
1%
#630000
0%
#635000
b111011 0
b111011 +
1%
#640000
0%
#645000
b111100 +
b111100 0
1%
#650000
0%
#655000
b111101 0
b111101 +
1%
#660000
0%
#665000
b111110 +
b111110 0
1%
#670000
0%
#675000
b111111 0
b111111 +
1%
#680000
0%
#685000
b1000000 +
b1000000 0
1%
#690000
0%
#695000
b1000001 0
b1000001 +
1%
#700000
0%
#705000
b1000010 +
b1000010 0
1%
#710000
0%
#715000
b1000011 0
b1000011 +
1%
#720000
0%
#725000
b1000100 +
b1000100 0
1%
#730000
0%
#735000
b1000101 0
b1000101 +
1%
#740000
0%
#745000
b1000110 +
b1000110 0
1%
#750000
0%
#755000
b1000111 0
b1000111 +
1%
#760000
0%
#765000
b1001000 +
b1001000 0
1%
#770000
0%
#775000
b1001001 0
b1001001 +
1%
#780000
0%
#785000
b1001010 +
b1001010 0
1%
#790000
0%
#795000
b1001011 0
b1001011 +
1%
#800000
0%
#805000
b1001100 +
b1001100 0
1%
#810000
0%
#815000
b1001101 0
b1001101 +
1%
#820000
0%
#825000
b1001110 +
b1001110 0
1%
#830000
0%
#835000
b1001111 0
b1001111 +
1%
#840000
0%
#845000
b1010000 +
b1010000 0
1%
#850000
0%
#855000
b1010001 0
b1010001 +
1%
#860000
0%
#865000
b1010010 +
b1010010 0
1%
#870000
0%
#875000
b1010011 0
b1010011 +
1%
#880000
0%
#885000
b1010100 +
b1010100 0
1%
#890000
0%
#895000
b1010101 0
b1010101 +
1%
#900000
0%
#905000
b1010110 +
b1010110 0
1%
#910000
0%
#915000
b1010111 0
b1010111 +
1%
#920000
0%
#925000
b1011000 +
b1011000 0
1%
#930000
0%
#935000
b1011001 0
b1011001 +
1%
#940000
0%
#945000
b1011010 +
b1011010 0
1%
#950000
0%
#955000
b1011011 0
b1011011 +
1%
#960000
0%
#965000
b1011100 +
b1011100 0
1%
#970000
0%
#975000
b1011101 0
b1011101 +
1%
#980000
0%
#985000
b1011110 +
b1011110 0
1%
#990000
0%
#995000
b1011111 0
b1011111 +
1%
#1000000
0%
#1005000
b1100000 +
b1100000 0
1%
#1010000
0%
#1015000
b1100001 0
b1100001 +
1%
#1020000
0%
#1025000
b1100010 +
b1100010 0
1%
#1030000
0%
#1035000
b1100011 0
b1100011 +
1%
#1040000
0%
#1045000
b1100100 +
b1100100 0
1%
#1050000
0%
#1055000
b1100101 0
b1100101 +
1%
#1060000
0%
#1065000
b1100110 +
b1100110 0
1%
#1070000
0%
#1075000
b1100111 0
b1100111 +
1%
#1080000
0%
#1085000
b1101000 +
b1101000 0
1%
#1090000
0%
#1095000
b1101001 0
b1101001 +
1%
#1100000
0%
#1105000
b1101010 +
b1101010 0
1%
#1110000
0%
#1115000
b1101011 0
b1101011 +
1%
#1120000
0%
#1125000
b1101100 +
b1101100 0
1%
#1130000
0%
#1135000
b1101101 0
b1101101 +
1%
#1140000
0%
#1145000
b1101110 +
b1101110 0
1%
#1150000
0%
#1155000
b1101111 0
b1101111 +
1%
#1160000
0%
#1165000
b1110000 +
b1110000 0
1%
#1170000
0%
#1175000
b1110001 0
b1110001 +
1%
#1180000
0%
#1185000
b1110010 +
b1110010 0
1%
#1190000
0%
#1195000
b1110011 0
b1110011 +
1%
#1200000
0%
#1205000
b1110100 +
b1110100 0
1%
#1210000
0%
#1215000
b1110101 0
b1110101 +
1%
#1220000
0%
#1225000
b1110110 +
b1110110 0
1%
#1230000
0%
#1235000
b1110111 0
b1110111 +
1%
#1240000
0%
#1245000
b1111000 +
b1111000 0
1%
#1250000
0%
#1255000
b1111001 0
b1111001 +
1%
#1260000
0%
#1265000
b1111010 +
b1111010 0
1%
#1270000
0%
#1275000
b1111011 0
b1111011 +
1%
#1280000
0%
#1285000
b1111100 +
b1111100 0
1%
#1290000
0%
#1295000
b1111101 0
b1111101 +
1%
#1300000
0%
#1305000
b1111110 +
b1111110 0
1%
#1310000
0%
#1315000
b1111111 0
b1111111 +
1%
#1320000
0%
#1325000
b10000000 +
b1111110 0
11
1%
#1330000
0%
#1335000
b1111101 0
b10000001 +
1%
#1340000
0%
#1345000
b10000010 +
b1111100 0
1%
#1350000
0%
#1355000
b1111011 0
b10000011 +
1%
#1360000
0%
#1365000
b10000100 +
b1111010 0
1%
#1370000
0%
#1375000
b1111001 0
b10000101 +
1%
#1380000
0%
#1385000
b10000110 +
b1111000 0
1%
#1390000
0%
#1395000
b1110111 0
b10000111 +
1%
#1400000
0%
#1405000
b10001000 +
b1110110 0
1%
#1410000
0%
#1415000
b1110101 0
b10001001 +
1%
#1420000
0%
#1425000
b10001010 +
b1110100 0
1%
#1430000
0%
#1435000
b1110011 0
b10001011 +
1%
#1440000
0%
#1445000
b10001100 +
b1110010 0
1%
#1450000
0%
#1455000
b1110001 0
b10001101 +
1%
#1460000
0%
#1465000
b10001110 +
b1110000 0
1%
#1470000
0%
#1475000
b1101111 0
b10001111 +
1%
#1480000
0%
#1485000
b10010000 +
b1101110 0
1%
#1490000
0%
#1495000
b1101101 0
b10010001 +
1%
#1500000
0%
#1505000
b10010010 +
b1101100 0
1%
#1510000
0%
#1515000
b1101011 0
b10010011 +
1%
#1520000
0%
#1525000
b10010100 +
b1101010 0
1%
#1530000
0%
#1535000
b1101001 0
b10010101 +
1%
#1540000
0%
#1545000
b10010110 +
b1101000 0
1%
#1550000
0%
#1555000
b1100111 0
b10010111 +
1%
#1560000
0%
#1565000
b10011000 +
b1100110 0
1%
#1570000
0%
#1575000
b1100101 0
b10011001 +
1%
#1580000
0%
#1585000
b10011010 +
b1100100 0
1%
#1590000
0%
#1595000
b1100011 0
b10011011 +
1%
#1600000
0%
#1605000
b10011100 +
b1100010 0
1%
#1610000
0%
#1615000
b1100001 0
b10011101 +
1%
#1620000
0%
#1625000
b10011110 +
b1100000 0
1%
#1630000
0%
#1635000
b1011111 0
b10011111 +
1%
#1640000
0%
#1645000
b10100000 +
b1011110 0
1%
#1650000
0%
#1655000
b1011101 0
b10100001 +
1%
#1660000
0%
#1665000
b10100010 +
b1011100 0
1%
#1670000
0%
#1675000
b1011011 0
b10100011 +
1%
#1680000
0%
#1685000
b10100100 +
b1011010 0
1%
#1690000
0%
#1695000
b1011001 0
b10100101 +
1%
#1700000
0%
#1705000
b10100110 +
b1011000 0
1%
#1710000
0%
#1715000
b1010111 0
b10100111 +
1%
#1720000
0%
#1725000
b10101000 +
b1010110 0
1%
#1730000
0%
#1735000
b1010101 0
b10101001 +
1%
#1740000
0%
#1745000
b10101010 +
b1010100 0
1%
#1750000
0%
#1755000
b1010011 0
b10101011 +
1%
#1760000
0%
#1765000
b10101100 +
b1010010 0
1%
#1770000
0%
#1775000
b1010001 0
b10101101 +
1%
#1780000
0%
#1785000
b10101110 +
b1010000 0
1%
#1790000
0%
#1795000
b1001111 0
b10101111 +
1%
#1800000
0%
#1805000
b10110000 +
b1001110 0
1%
#1810000
0%
#1815000
b1001101 0
b10110001 +
1%
#1820000
0%
#1825000
b10110010 +
b1001100 0
1%
#1830000
0%
#1835000
b1001011 0
b10110011 +
1%
#1840000
0%
#1845000
b10110100 +
b1001010 0
1%
#1850000
0%
#1855000
b1001001 0
b10110101 +
1%
#1860000
0%
#1865000
b10110110 +
b1001000 0
1%
#1870000
0%
#1875000
b1000111 0
b10110111 +
1%
#1880000
0%
#1885000
b10111000 +
b1000110 0
1%
#1890000
0%
#1895000
b1000101 0
b10111001 +
1%
#1900000
0%
#1905000
b10111010 +
b1000100 0
1%
#1910000
0%
#1915000
b1000011 0
b10111011 +
1%
#1920000
0%
#1925000
b10111100 +
b1000010 0
1%
#1930000
0%
#1935000
b1000001 0
b10111101 +
1%
#1940000
0%
#1945000
b10111110 +
b1000000 0
1%
#1950000
0%
#1955000
b111111 0
b10111111 +
1%
#1960000
0%
#1965000
b11000000 +
b111110 0
1%
#1970000
0%
#1975000
b111101 0
b11000001 +
1%
#1980000
0%
#1985000
b11000010 +
b111100 0
1%
#1990000
0%
#1995000
b111011 0
b11000011 +
1%
#2000000
0%
#2005000
b11000100 +
b111010 0
1%
#2010000
0%
#2015000
b111001 0
b11000101 +
1%
#2020000
0%
#2025000
b11000110 +
b111000 0
1%
#2030000
0%
#2035000
b110111 0
b11000111 +
1%
#2040000
0%
#2045000
b11001000 +
b110110 0
1%
#2050000
0%
#2055000
b110101 0
b11001001 +
1%
#2060000
0%
#2065000
b11001010 +
b110100 0
1%
#2070000
0%
#2075000
b110011 0
b11001011 +
1%
#2080000
0%
#2085000
b11001100 +
b110010 0
1%
#2090000
0%
#2095000
b110001 0
b11001101 +
1%
#2100000
0%
#2105000
b11001110 +
b110000 0
1%
#2110000
0%
#2115000
b101111 0
b11001111 +
1%
#2120000
0%
#2125000
b11010000 +
b101110 0
1%
#2130000
0%
#2135000
b101101 0
b11010001 +
1%
#2140000
0%
#2145000
b11010010 +
b101100 0
1%
#2150000
0%
#2155000
b101011 0
b11010011 +
1%
#2160000
0%
#2165000
b11010100 +
b101010 0
1%
#2170000
0%
#2175000
b101001 0
b11010101 +
1%
#2180000
0%
#2185000
b11010110 +
b101000 0
1%
#2190000
0%
#2195000
b100111 0
b11010111 +
1%
#2200000
0%
#2205000
b11011000 +
b100110 0
1%
#2210000
0%
#2215000
b100101 0
b11011001 +
1%
#2220000
0%
#2225000
b11011010 +
b100100 0
1%
#2230000
0%
#2235000
b100011 0
b11011011 +
1%
#2240000
0%
#2245000
b11011100 +
b100010 0
1%
#2250000
0%
#2255000
b100001 0
b11011101 +
1%
#2260000
0%
#2265000
b11011110 +
b100000 0
1%
#2270000
0%
#2275000
b11111 0
b11011111 +
1%
#2280000
0%
#2285000
b11100000 +
b11110 0
1%
#2290000
0%
#2295000
b11101 0
b11100001 +
1%
#2300000
0%
#2305000
b11100010 +
b11100 0
1%
#2310000
0%
#2315000
b11011 0
b11100011 +
1%
#2320000
0%
#2325000
b11100100 +
b11010 0
1%
#2330000
0%
#2335000
b11001 0
b11100101 +
1%
#2340000
0%
#2345000
b11100110 +
b11000 0
1%
#2350000
0%
#2355000
b10111 0
b11100111 +
1%
#2360000
0%
#2365000
b11101000 +
b10110 0
1%
#2370000
0%
#2375000
b10101 0
b11101001 +
1%
#2380000
0%
#2385000
b11101010 +
b10100 0
1%
#2390000
0%
#2395000
b10011 0
b11101011 +
1%
#2400000
0%
#2405000
b11101100 +
b10010 0
1%
#2410000
0%
#2415000
b10001 0
b11101101 +
1%
#2420000
0%
#2425000
b11101110 +
b10000 0
1%
#2430000
0%
#2435000
b1111 0
b11101111 +
1%
#2440000
0%
#2445000
b11110000 +
b1110 0
1%
#2450000
0%
#2455000
b1101 0
b11110001 +
1%
#2460000
0%
#2465000
b11110010 +
b1100 0
1%
#2470000
0%
#2475000
b1011 0
b11110011 +
1%
#2480000
0%
#2485000
b11110100 +
b1010 0
1%
#2490000
0%
#2495000
b1001 0
b11110101 +
1%
#2500000
0%
#2505000
b11110110 +
b1000 0
1%
#2510000
0%
#2515000
b111 0
b11110111 +
1%
#2520000
0%
#2525000
b11111000 +
b110 0
1%
#2530000
0%
#2535000
b101 0
b11111001 +
1%
#2540000
0%
#2545000
b11111010 +
b100 0
1%
#2550000
0%
#2555000
b11 0
b11111011 +
1%
#2560000
0%
#2565000
b11111100 +
b10 0
1%
#2570000
0%
#2575000
b1 0
b11111101 +
1%
#2580000
0%
#2585000
b11111110 +
b0 0
1%
#2590000
0%
#2595000
b1 0
01
b11111111 +
1%
#2600000
0%
#2605000
b0 +
b10 0
1%
#2610000
0%
#2615000
b11 0
b1 +
1%
#2620000
0%
#2625000
b10 +
b100 0
1%
#2630000
0%
#2635000
b101 0
b11 +
1%
#2640000
0%
#2645000
b100 +
b110 0
1%
#2650000
0%
#2655000
b111 0
b101 +
1%
#2660000
0%
#2665000
b110 +
b1000 0
1%
#2670000
0%
#2675000
b1001 0
b111 +
1%
#2680000
0%
#2685000
b1000 +
b1010 0
1%
#2690000
0%
#2695000
b1011 0
b1001 +
1%
#2700000
0%
#2705000
b1010 +
b1100 0
1%
#2710000
0%
#2715000
b1101 0
b1011 +
1%
#2720000
0%
#2725000
b1100 +
b1110 0
1%
#2730000
0%
#2735000
b1111 0
b1101 +
1%
#2740000
0%
#2745000
b1110 +
b10000 0
1%
#2750000
0%
#2755000
b10001 0
b1111 +
1%
#2760000
0%
#2765000
b10000 +
b10010 0
1%
#2770000
0%
#2775000
b10011 0
b10001 +
1%
#2780000
0%
#2785000
b10010 +
b10100 0
1%
#2790000
0%
#2795000
b10101 0
b10011 +
1%
#2800000
0%
#2805000
b10100 +
b10110 0
1%
#2810000
0%
#2815000
b10111 0
b10101 +
1%
#2820000
0%
#2825000
b10110 +
b11000 0
1%
#2830000
0%
#2835000
b11001 0
b10111 +
1%
#2840000
0%
#2845000
b11000 +
b11010 0
1%
#2850000
0%
#2855000
b11011 0
b11001 +
1%
#2860000
0%
#2865000
b11010 +
b11100 0
1%
#2870000
0%
#2875000
b11101 0
b11011 +
1%
#2880000
0%
#2885000
b11100 +
b11110 0
1%
#2890000
0%
#2895000
b11111 0
b11101 +
1%
#2900000
0%
#2905000
b11110 +
b100000 0
1%
#2910000
0%
#2915000
b100001 0
b11111 +
1%
#2920000
0%
#2925000
b100000 +
b100010 0
1%
#2930000
0%
#2935000
b100011 0
b100001 +
1%
#2940000
0%
#2945000
b100010 +
b100100 0
1%
#2950000
0%
#2955000
b100101 0
b100011 +
1%
#2960000
0%
#2965000
b100100 +
b100110 0
1%
#2970000
0%
#2975000
b100111 0
b100101 +
1%
#2980000
0%
#2985000
b100110 +
b101000 0
1%
#2990000
0%
#2995000
b101001 0
b100111 +
1%
#3000000
0%
#3005000
b101000 +
b101010 0
1%
#3010000
0%
#3015000
b101011 0
b101001 +
1%
#3020000
0%
#3025000
b101010 +
b101100 0
1%
#3030000
0%
#3035000
b101101 0
b101011 +
1%
#3040000
0%
#3045000
b101100 +
b101110 0
1%
#3050000
0%
#3055000
b101111 0
b101101 +
1%
#3060000
0%
#3065000
b101110 +
b110000 0
1%
#3070000
0%
#3075000
b110001 0
b101111 +
1%
#3080000
0%
#3085000
b110000 +
b110010 0
1%
#3090000
0%
#3095000
b110011 0
b110001 +
1%
#3100000
0%
#3105000
b110010 +
b110100 0
1%
#3110000
0%
#3115000
b110101 0
b110011 +
1%
#3120000
0%
#3125000
b110100 +
b110110 0
1%
#3130000
0%
#3135000
b110111 0
b110101 +
1%
#3140000
0%
#3145000
b110110 +
b111000 0
1%
#3150000
0%
#3155000
b111001 0
b110111 +
1%
#3160000
0%
#3165000
b111000 +
b111010 0
1%
#3170000
0%
#3175000
b111011 0
b111001 +
1%
#3180000
0%
#3185000
b111010 +
b111100 0
1%
#3190000
0%
#3195000
b111101 0
b111011 +
1%
#3200000
0%
#3205000
b111100 +
b111110 0
1%
#3210000
0%
#3215000
b111111 0
b111101 +
1%
#3220000
0%
#3225000
b111110 +
b1000000 0
1%
#3230000
0%
#3235000
b1000001 0
b111111 +
1%
#3240000
0%
#3245000
b1000000 +
b1000010 0
1%
#3250000
0%
#3255000
b1000011 0
b1000001 +
1%
#3260000
0%
#3265000
b1000010 +
b1000100 0
1%
#3270000
0%
#3275000
b1000101 0
b1000011 +
1%
#3280000
0%
#3285000
b1000100 +
b1000110 0
1%
#3290000
0%
#3295000
b1000111 0
b1000101 +
1%
#3300000
0%
#3305000
b1000110 +
b1001000 0
1%
#3310000
0%
#3315000
b1001001 0
b1000111 +
1%
#3320000
0%
#3325000
b1001000 +
b1001010 0
1%
#3330000
0%
#3335000
b1001011 0
b1001001 +
1%
#3340000
0%
#3345000
b1001010 +
b1001100 0
1%
#3350000
0%
#3355000
b1001101 0
b1001011 +
1%
#3360000
0%
#3365000
b1001100 +
b1001110 0
1%
#3370000
0%
#3375000
b1001111 0
b1001101 +
1%
#3380000
0%
#3385000
b1001110 +
b1010000 0
1%
#3390000
0%
#3395000
b1010001 0
b1001111 +
1%
#3400000
0%
#3405000
b1010000 +
b1010010 0
1%
#3410000
0%
#3415000
b1010011 0
b1010001 +
1%
#3420000
0%
#3425000
b1010010 +
b1010100 0
1%
#3430000
0%
#3435000
b1010101 0
b1010011 +
1%
#3440000
0%
#3445000
b1010100 +
b1010110 0
1%
#3450000
0%
#3455000
b1010111 0
b1010101 +
1%
#3460000
0%
#3465000
b1010110 +
b1011000 0
1%
#3470000
0%
#3475000
b1011001 0
b1010111 +
1%
#3480000
0%
#3485000
b1011000 +
b1011010 0
1%
#3490000
0%
#3495000
b1011011 0
b1011001 +
1%
#3500000
0%
#3505000
b1011010 +
b1011100 0
1%
#3510000
0%
#3515000
b1011101 0
b1011011 +
1%
#3520000
0%
#3525000
b1011100 +
b1011110 0
1%
#3530000
0%
#3535000
b1011111 0
b1011101 +
1%
#3540000
0%
#3545000
b1011110 +
b1100000 0
1%
#3550000
0%
#3555000
b1100001 0
b1011111 +
1%
#3560000
0%
#3565000
b1100000 +
b1100010 0
1%
#3570000
0%
#3575000
b1100011 0
b1100001 +
1%
#3580000
0%
#3585000
b1100010 +
b1100100 0
1%
#3590000
0%
#3595000
b1100101 0
b1100011 +
1%
#3600000
0%
#3605000
b1100100 +
b1100110 0
1%
#3610000
0%
#3615000
b1100111 0
b1100101 +
1%
#3620000
0%
#3625000
b1100110 +
b1101000 0
1%
#3630000
0%
#3635000
b1101001 0
b1100111 +
1%
#3640000
0%
#3645000
b1101000 +
b1101010 0
1%
#3650000
0%
#3655000
b1101011 0
b1101001 +
1%
#3660000
0%
#3665000
b1101010 +
b1101100 0
1%
#3670000
0%
#3675000
b1101101 0
b1101011 +
1%
#3680000
0%
#3685000
b1101100 +
b1101110 0
1%
#3690000
0%
#3695000
b1101111 0
b1101101 +
1%
#3700000
0%
#3705000
b1101110 +
b1110000 0
1%
#3710000
0%
#3715000
b1110001 0
b1101111 +
1%
#3720000
0%
#3725000
b1110000 +
b1110010 0
1%
#3730000
0%
#3735000
b1110011 0
b1110001 +
1%
#3740000
0%
#3745000
b1110010 +
b1110100 0
1%
#3750000
0%
#3755000
b1110101 0
b1110011 +
1%
#3760000
0%
#3765000
b1110100 +
b1110110 0
1%
#3770000
0%
#3775000
b1110111 0
b1110101 +
1%
#3780000
0%
#3785000
b1110110 +
b1111000 0
1%
#3790000
0%
#3795000
b1111001 0
b1110111 +
1%
#3800000
0%
#3805000
b1111000 +
b1111010 0
1%
#3810000
0%
#3815000
b1111011 0
b1111001 +
1%
#3820000
0%
#3825000
b1111010 +
b1111100 0
1%
#3830000
0%
#3835000
b1111101 0
b1111011 +
1%
#3840000
0%
#3845000
b1111100 +
b1111110 0
1%
#3850000
0%
#3855000
b1111111 0
b1111101 +
1%
#3860000
0%
#3865000
b1111110 +
b1111110 0
11
1%
#3870000
0%
#3875000
b1111101 0
b1111111 +
1%
#3880000
0%
#3885000
b10000000 +
b1111100 0
1%
#3890000
0%
#3895000
b1111011 0
b10000001 +
1%
#3900000
0%
#3905000
b10000010 +
b1111010 0
1%
#3910000
0%
#3915000
b1111001 0
b10000011 +
1%
#3920000
0%
#3925000
b10000100 +
b1111000 0
1%
#3930000
0%
#3935000
b1110111 0
b10000101 +
1%
#3940000
0%
#3945000
b10000110 +
b1110110 0
1%
#3950000
0%
#3955000
b1110101 0
b10000111 +
1%
#3960000
0%
#3965000
b10001000 +
b1110100 0
1%
#3970000
0%
#3975000
b1110011 0
b10001001 +
1%
#3980000
0%
#3985000
b10001010 +
b1110010 0
1%
#3990000
0%
#3995000
b1110001 0
b10001011 +
1%
#4000000
0%
#4005000
b10001100 +
b1110000 0
1%
#4010000
0%
#4015000
b1101111 0
b10001101 +
1%
#4020000
0%
#4025000
b10001110 +
b1101110 0
1%
#4030000
0%
#4035000
b1101101 0
b10001111 +
1%
#4040000
0%
#4045000
b10010000 +
b1101100 0
1%
#4050000
0%
#4055000
b1101011 0
b10010001 +
1%
#4060000
0%
#4065000
b10010010 +
b1101010 0
1%
#4070000
0%
#4075000
b1101001 0
b10010011 +
1%
#4080000
0%
#4085000
b10010100 +
b1101000 0
1%
#4090000
0%
#4095000
b1100111 0
b10010101 +
1%
#4100000
0%
#4105000
b10010110 +
b1100110 0
1%
#4110000
0%
#4115000
b1100101 0
b10010111 +
1%
#4120000
0%
#4125000
b10011000 +
b1100100 0
1%
#4130000
0%
#4135000
b1100011 0
b10011001 +
1%
#4140000
0%
#4145000
b10011010 +
b1100010 0
1%
#4150000
0%
#4155000
b1100001 0
b10011011 +
1%
#4160000
0%
#4165000
b10011100 +
b1100000 0
1%
#4170000
0%
#4175000
b1011111 0
b10011101 +
1%
#4180000
0%
#4185000
b10011110 +
b1011110 0
1%
#4190000
0%
#4195000
b1011101 0
b10011111 +
1%
#4200000
0%
#4205000
b10100000 +
b1011100 0
1%
#4210000
0%
#4215000
b1011011 0
b10100001 +
1%
#4220000
0%
#4225000
b10100010 +
b1011010 0
1%
#4230000
0%
#4235000
b1011001 0
b10100011 +
1%
#4240000
0%
#4245000
b10100100 +
b1011000 0
1%
#4250000
0%
#4255000
b1010111 0
b10100101 +
1%
#4260000
0%
#4265000
b10100110 +
b1010110 0
1%
#4270000
0%
#4275000
b1010101 0
b10100111 +
1%
#4280000
0%
#4285000
b10101000 +
b1010100 0
1%
#4290000
0%
#4295000
b1010011 0
b10101001 +
1%
#4300000
0%
#4305000
b10101010 +
b1010010 0
1%
#4310000
0%
#4315000
b1010001 0
b10101011 +
1%
#4320000
0%
#4325000
b10101100 +
b1010000 0
1%
#4330000
0%
#4335000
b1001111 0
b10101101 +
1%
#4340000
0%
