Unselected Hardware/edge_q_decoder.v
module edge_q_decoder (
    input  wire clk,
    input  wire rst,
    input  wire A_raw,
    input  wire B_raw,
    output reg signed [31:0] position
);

    // Synchronizers for A and B (2-stage)
    reg A_sync_0, A_sync_1;
    reg B_sync_0, B_sync_1;
    always @(posedge clk) begin
        A_sync_0 <= A_raw;
        A_sync_1 <= A_sync_0;
        B_sync_0 <= B_raw;
        B_sync_1 <= B_sync_0;
    end

    // Shift registers for edge detection
    reg [1:0] A_shift, B_shift;
    always @(posedge clk) begin
        A_shift <= {A_shift[0], A_sync_1};
        B_shift <= {B_shift[0], B_sync_1};
    end

    wire A_rise = (A_shift == 2'b01);
    wire A_fall = (A_shift == 2'b10);
    wire B_rise = (B_shift == 2'b01);
    wire B_fall = (B_shift == 2'b10);

    // Position update logic (4x decoding)
    always @(posedge clk) begin
        if (rst) begin
            position <= 0;
        end else begin
            if (A_rise)
                position <= position + (B_sync_1 ? -1 : 1);
            else if (A_fall)
                position <= position + (B_sync_1 ? 1 : -1);
            else if (B_rise)
                position <= position + (A_sync_1 ? 1 : -1);
            else if (B_fall)
                position <= position + (A_sync_1 ? -1 : 1);
        end
    end

endmodule

Unselected Hardware/tb_edge_q_decoder.v
`timescale 1ns / 1ps

module tb_edge_q_decoder;

    reg clk = 0;
    reg rst = 1;
    reg A_raw = 0, B_raw = 0;
    wire signed [31:0] position;

    localparam CLK_PERIOD = 10;

    edge_q_decoder uut (
        .clk(clk),
        .rst(rst),
        .A_raw(A_raw),
        .B_raw(B_raw),
        .position(position)
    );

    // Clock generation
    always #(CLK_PERIOD/2) clk = ~clk;

    // Generate quadrature waveform
    task quadrature_step(input integer steps, input integer direction);
        integer i;
        begin
            for (i = 0; i < steps; i = i + 1) begin
                if (direction == 1) begin
                    // Forward step sequence: 00 → 01 → 11 → 10 → 00
                    {A_raw, B_raw} = 2'b00; #(CLK_PERIOD);
                    {A_raw, B_raw} = 2'b01; #(CLK_PERIOD);
                    {A_raw, B_raw} = 2'b11; #(CLK_PERIOD);
                    {A_raw, B_raw} = 2'b10; #(CLK_PERIOD);
                end else begin
                    // Reverse step sequence: 00 → 10 → 11 → 01 → 00
                    {A_raw, B_raw} = 2'b00; #(CLK_PERIOD);
                    {A_raw, B_raw} = 2'b10; #(CLK_PERIOD);
                    {A_raw, B_raw} = 2'b11; #(CLK_PERIOD);
                    {A_raw, B_raw} = 2'b01; #(CLK_PERIOD);
                end
            end
            {A_raw, B_raw} = 2'b00; #(CLK_PERIOD);
        end
    endtask

    initial begin
        $dumpfile("edge_q_decoder.vcd");
        $dumpvars(0, tb_edge_q_decoder);

        #(10 * CLK_PERIOD);
        rst = 0;

        // Forward motion: 10,000 steps
        quadrature_step(100, 1);

        // Wait briefly
        #(100 * CLK_PERIOD);

        // Reverse motion: 10,000 steps
        quadrature_step(100, 0);

        #(100 * CLK_PERIOD);
        $display("Final position: %0d", position);  // Should be 0
        $finish;
    end

endmodule

Unselected Hardware/edge_q_decoder.vcd
$date
	Tue Jul 29 17:36:44 2025
$end
$version
	Icarus Verilog
$end
$timescale
	1ps
$end
$scope module tb_edge_q_decoder $end
$var wire 32 ! position [31:0] $end
$var parameter 32 " CLK_PERIOD $end
$var reg 1 # A_raw $end
$var reg 1 $ B_raw $end
$var reg 1 % clk $end
$var reg 1 & rst $end
$scope module uut $end
$var wire 1 # A_raw $end
$var wire 1 $ B_raw $end
$var wire 1 % clk $end
$var wire 1 & rst $end
$var wire 1 ' B_rise $end
$var wire 1 ( B_fall $end
$var wire 1 ) A_rise $end
$var wire 1 * A_fall $end
$var reg 2 + A_shift [1:0] $end
$var reg 1 , A_sync_0 $end
$var reg 1 - A_sync_1 $end
$var reg 2 . B_shift [1:0] $end
$var reg 1 / B_sync_0 $end
$var reg 1 0 B_sync_1 $end
$var reg 32 1 position [31:0] $end
$upscope $end
$scope task quadrature_step $end
$var integer 32 2 direction [31:0] $end
$var integer 32 3 i [31:0] $end
$var integer 32 4 steps [31:0] $end
$upscope $end
$upscope $end
$enddefinitions $end
$comment Show the parameter values. $end
$dumpall
b1010 "
$end
#0
$dumpvars
bx 4
bx 3
bx 2
bx 1
x0
x/
bx .
x-
x,
bx +
x*
x)
x(
x'
1&
0%
0$
0#
bx !
$end
#5000
0/
0,
b0 !
b0 1
1%
#10000
0%
#15000
00
0-
1%
#20000
0%
#25000
0'
bx0 .
0)
bx0 +
1%
#30000
0%
#35000
0(
b0 .
0*
b0 +
1%
#40000
0%
#45000
1%
#50000
0%
#55000
1%
#60000
0%
#65000
1%
#70000
0%
#75000
1%
#80000
0%
#85000
1%
#90000
0%
#95000
1%
#100000
0%
b0 3
b1 2
b1100100 4
0&
#105000
1%
#110000
0%
1$
#115000
1/
1%
#120000
0%
1#
#125000
10
1,
1%
#130000
0%
0$
#135000
1'
b1 .
0/
1-
1%
#140000
0%
0#
b1 3
#145000
00
0,
0'
b11 .
1)
b1 +
b1 !
b1 1
1%
#150000
0%
1$
#155000
b10 !
b10 1
1(
b10 .
0)
b11 +
1/
0-
1%
#160000
0%
1#
#165000
10
1,
0(
b0 .
1*
b10 +
b11 !
b11 1
1%
#170000
0%
0$
#175000
b100 !
b100 1
1'
b1 .
0*
b0 +
0/
1-
1%
#180000
0%
0#
b10 3
#185000
00
0,
0'
b11 .
1)
b1 +
b101 !
b101 1
1%
#190000
0%
1$
#195000
b110 !
b110 1
1(
b10 .
0)
b11 +
1/
0-
1%
#200000
0%
1#
#205000
10
1,
0(
b0 .
1*
b10 +
b111 !
b111 1
1%
#210000
0%
0$
#215000
b1000 !
b1000 1
1'
b1 .
0*
b0 +
0/
1-
1%
#220000
0%
0#
b11 3
#225000
00
0,
0'
b11 .
1)
b1 +
b1001 !
b1001 1
1%
#230000
0%
1$
#235000
b1010 !
b1010 1
1(
b10 .
0)
b11 +
1/
0-
1%
#240000
0%
1#
#245000
10
1,
0(
b0 .
1*
b10 +
b1011 !
b1011 1
1%
#250000
0%
0$
#255000
b1100 !
b1100 1
1'
b1 .
0*
b0 +
0/
1-
1%
#260000
0%
0#
b100 3
#265000
00
0,
0'
b11 .
1)
b1 +
b1101 !
b1101 1
1%
#270000
0%
1$
#275000
b1110 !
b1110 1
1(
b10 .
0)
b11 +
1/
0-
1%
#280000
0%
1#
#285000
10
1,
0(
b0 .
1*
b10 +
b1111 !
b1111 1
1%
#290000
0%
0$
#295000
b10000 !
b10000 1
1'
b1 .
0*
b0 +
0/
1-
1%
#300000
0%
0#
b101 3
#305000
00
0,
0'
b11 .
1)
b1 +
b10001 !
b10001 1
1%
#310000
0%
1$
#315000
b10010 !
b10010 1
1(
b10 .
0)
b11 +
1/
0-
1%
#320000
0%
1#
#325000
10
1,
0(
b0 .
1*
b10 +
b10011 !
b10011 1
1%
#330000
0%
0$
#335000
b10100 !
b10100 1
1'
b1 .
0*
b0 +
0/
1-
1%
#340000
0%
0#
b110 3
#345000
00
0,
0'
b11 .
1)
b1 +
b10101 !
b10101 1
1%
#350000
0%
1$
#355000
b10110 !
b10110 1
1(
b10 .
0)
b11 +
1/
0-
1%
#360000
0%
1#
#365000
10
1,
0(
b0 .
1*
b10 +
b10111 !
b10111 1
1%
#370000
0%
0$
#375000
b11000 !
b11000 1
1'
b1 .
0*
b0 +
0/
1-
1%
#380000
0%
0#
b111 3
#385000
00
0,
0'
b11 .
1)
b1 +
b11001 !
b11001 1
1%
#390000
0%
1$
#395000
b11010 !
b11010 1
1(
b10 .
0)
b11 +
1/
0-
1%
#400000
0%
1#
#405000
10
1,
0(
b0 .
1*
b10 +
b11011 !
b11011 1
1%
#410000
0%
0$
#415000
b11100 !
b11100 1
1'
b1 .
0*
b0 +
0/
1-
1%
#420000
0%
0#
b1000 3
#425000
00
0,
0'
b11 .
1)
b1 +
b11101 !
b11101 1
1%
#430000
0%
1$
#435000
b11110 !
b11110 1
1(
b10 .
0)
b11 +
1/
0-
1%
#440000
0%
1#
#445000
10
1,
0(
b0 .
1*
b10 +
b11111 !
b11111 1
1%
#450000
0%
0$
#455000
b100000 !
b100000 1
1'
b1 .
0*
b0 +
0/
1-
1%
#460000
0%
0#
b1001 3
#465000
00
0,
0'
b11 .
1)
b1 +
b100001 !
b100001 1
1%
#470000
0%
1$
#475000
b100010 !
b100010 1
1(
b10 .
0)
b11 +
1/
0-
1%
#480000
0%
1#
#485000
10
1,
0(
b0 .
1*
b10 +
b100011 !
b100011 1
1%
#490000
0%
0$
#495000
b100100 !
b100100 1
1'
b1 .
0*
b0 +
0/
1-
1%
#500000
0%
0#
b1010 3
#505000
00
0,
0'
b11 .
1)
b1 +
b100101 !
b100101 1
1%
#510000
0%
1$
#515000
b100110 !
b100110 1
1(
b10 .
0)
b11 +
1/
0-
1%
#520000
0%
1#
#525000
10
1,
0(
b0 .
1*
b10 +
b100111 !
b100111 1
1%
#530000
0%
0$
#535000
b101000 !
b101000 1
1'
b1 .
0*
b0 +
0/
1-
1%
#540000
0%
0#
b1011 3
#545000
00
0,
0'
b11 .
1)
b1 +
b101001 !
b101001 1
1%
#550000
0%
1$
#555000
b101010 !
b101010 1
1(
b10 .
0)
b11 +
1/
0-
1%
#560000
0%
1#
#565000
10
1,
0(
b0 .
1*
b10 +
b101011 !
b101011 1
1%
#570000
0%
0$
#575000
b101100 !
b101100 1
1'
b1 .
0*
b0 +
0/
1-
1%
#580000
0%
0#
b1100 3
#585000
00
0,
0'
b11 .
1)
b1 +
b101101 !
b101101 1
1%
#590000
0%
1$
#595000
b101110 !
b101110 1
1(
b10 .
0)
b11 +
1/
0-
1%
#600000
0%
1#
#605000
10
1,
0(
b0 .
1*
b10 +
b101111 !
b101111 1
1%
#610000
0%
0$
#615000
b110000 !
b110000 1
1'
b1 .
0*
b0 +
0/
1-
1%
#620000
0%
0#
b1101 3
#625000
00
0,
0'
b11 .
1)
b1 +
b110001 !
b110001 1
1%
#630000
0%
1$
#635000
b110010 !
b110010 1
1(
b10 .
0)
b11 +
1/
0-
1%
#640000
0%
1#
#645000
10
1,
0(
b0 .
1*
b10 +
b110011 !
b110011 1
1%
#650000
0%
0$
#655000
b110100 !
b110100 1
1'
b1 .
0*
b0 +
0/
1-
1%
#660000
0%
0#
b1110 3
#665000
00
0,
0'
b11 .
1)
b1 +
b110101 !
b110101 1
1%
#670000
0%
1$
#675000
b110110 !
b110110 1
1(
b10 .
0)
b11 +
1/
0-
1%
#680000
0%
1#
#685000
10
1,
0(
b0 .
1*
b10 +
b110111 !
b110111 1
1%
#690000
0%
0$
#695000
b111000 !
b111000 1
1'
b1 .
0*
b0 +
0/
1-
1%
#700000
0%
0#
b1111 3
#705000
00
0,
0'
b11 .
1)
b1 +
b111001 !
b111001 1
1%
#710000
0%
1$
#715000
b111010 !
b111010 1
1(
b10 .
0)
b11 +
1/
0-
1%
#720000
0%
1#
#725000
10
1,
0(
b0 .
1*
b10 +
b111011 !
b111011 1
1%
#730000
0%
0$
#735000
b111100 !
b111100 1
1'
b1 .
0*
b0 +
0/
1-
1%
#740000
0%
0#
b10000 3
#745000
00
0,
0'
b11 .
1)
b1 +
b111101 !
b111101 1
1%
#750000
0%
1$
#755000
b111110 !
b111110 1
1(
b10 .
0)
b11 +
1/
0-
1%
#760000
0%
1#
#765000
10
1,
0(
b0 .
1*
b10 +
b111111 !
b111111 1
1%
#770000
0%
0$
#775000
b1000000 !
b1000000 1
1'
b1 .
0*
b0 +
0/
1-
1%
#780000
0%
0#
b10001 3
#785000
00
0,
0'
b11 .
1)
b1 +
b1000001 !
b1000001 1
1%
#790000
0%
1$
#795000
b1000010 !
b1000010 1
1(
b10 .
0)
b11 +
1/
0-
1%
#800000
0%
1#
#805000
10
1,
0(
b0 .
1*
b10 +
b1000011 !
b1000011 1
1%
#810000
0%
0$
#815000
b1000100 !
b1000100 1
1'
b1 .
0*
b0 +
0/
1-
1%
#820000
0%
0#
b10010 3
#825000
00
0,
0'
b11 .
1)
b1 +
b1000101 !
b1000101 1
1%
#830000
0%
1$
#835000
b1000110 !
b1000110 1
1(
b10 .
0)
b11 +
1/
0-
1%
#840000
0%
1#
#845000
10
1,
0(
b0 .
1*
b10 +
b1000111 !
b1000111 1
1%
#850000
0%
0$
#855000
b1001000 !
b1001000 1
1'
b1 .
0*
b0 +
0/
1-
1%
#860000
0%
0#
b10011 3
#865000
00
0,
0'
b11 .
1)
b1 +
b1001001 !
b1001001 1
1%
#870000
0%
1$
#875000
b1001010 !
b1001010 1
1(
b10 .
0)
b11 +
1/
0-
1%
#880000
0%
1#
#885000
10
1,
0(
b0 .
1*
b10 +
b1001011 !
b1001011 1
1%
#890000
0%
0$
#895000
b1001100 !
b1001100 1
1'
b1 .
0*
b0 +
0/
1-
1%
#900000
0%
0#
b10100 3
#905000
00
0,
0'
b11 .
1)
b1 +
b1001101 !
b1001101 1
1%
#910000
0%
1$
#915000
b1001110 !
b1001110 1
1(
b10 .
0)
b11 +
1/
0-
1%
#920000
0%
1#
#925000
10
1,
0(
b0 .
1*
b10 +
b1001111 !
b1001111 1
1%
#930000
0%
0$
#935000
b1010000 !
b1010000 1
1'
b1 .
0*
b0 +
0/
1-
1%
#940000
0%
0#
b10101 3
#945000
00
0,
0'
b11 .
1)
b1 +
b1010001 !
b1010001 1
1%
#950000
0%
1$
#955000
b1010010 !
b1010010 1
1(
b10 .
0)
b11 +
1/
0-
1%
#960000
0%
1#
#965000
10
1,
0(
b0 .
1*
b10 +
b1010011 !
b1010011 1
1%
#970000
0%
0$
#975000
b1010100 !
b1010100 1
1'
b1 .
0*
b0 +
0/
1-
1%
#980000
0%
0#
b10110 3
#985000
00
0,
0'
b11 .
1)
b1 +
b1010101 !
b1010101 1
1%
#990000
0%
1$
#995000
b1010110 !
b1010110 1
1(
b10 .
0)
b11 +
1/
0-
1%
#1000000
0%
1#
#1005000
10
1,
0(
b0 .
1*
b10 +
b1010111 !
b1010111 1
1%
#1010000
0%
0$
#1015000
b1011000 !
b1011000 1
1'
b1 .
0*
b0 +
0/
1-
1%
#1020000
0%
0#
b10111 3
#1025000
00
0,
0'
b11 .
1)
b1 +
b1011001 !
b1011001 1
1%
#1030000
0%
1$
#1035000
b1011010 !
b1011010 1
1(
b10 .
0)
b11 +
1/
0-
1%
#1040000
0%
1#
#1045000
10
1,
0(
b0 .
1*
b10 +
b1011011 !
b1011011 1
1%
#1050000
0%
0$
#1055000
b1011100 !
b1011100 1
1'
b1 .
0*
b0 +
0/
1-
1%
#1060000
0%
0#
b11000 3
#1065000
00
0,
0'
b11 .
1)
b1 +
b1011101 !
b1011101 1
1%
#1070000
0%
1$
#1075000
b1011110 !
b1011110 1
1(
b10 .
0)
b11 +
1/
0-
1%
#1080000
0%
1#
#1085000
10
1,
0(
b0 .
1*
b10 +
b1011111 !
b1011111 1
1%
#1090000
0%
0$
#1095000
b1100000 !
b1100000 1
1'
b1 .
0*
b0 +
0/
1-
1%
#1100000
0%
0#
b11001 3
#1105000
00
0,
0'
b11 .
1)
b1 +
b1100001 !
b1100001 1
1%
#1110000
0%
1$
#1115000
b1100010 !
b1100010 1
1(
b10 .
0)
b11 +
1/
0-
1%
#1120000
0%
1#
#1125000
10
1,
0(
b0 .
1*
b10 +
b1100011 !
b1100011 1
1%
#1130000
0%
0$
#1135000
b1100100 !
b1100100 1
1'
b1 .
0*
b0 +
0/
1-
1%
#1140000
0%
0#
b11010 3
#1145000
00
0,
0'
b11 .
1)
b1 +
b1100101 !
b1100101 1
1%
#1150000
0%
1$
#1155000
b1100110 !
b1100110 1
1(
b10 .
0)
b11 +
1/
0-
1%
#1160000
0%
1#
#1165000
10
1,
0(
b0 .
1*
b10 +
b1100111 !
b1100111 1
1%
#1170000
0%
0$
#1175000
b1101000 !
b1101000 1
1'
b1 .
0*
b0 +
0/
1-
1%
#1180000
0%
0#
b11011 3
#1185000
00
0,
0'
b11 .
1)
b1 +
b1101001 !
b1101001 1
1%
#1190000
0%
1$
#1195000
b1101010 !
b1101010 1
1(
b10 .
0)
b11 +
1/
0-
1%
#1200000
0%
1#
#1205000
10
1,
0(
b0 .
1*
b10 +
b1101011 !
b1101011 1
1%
#1210000
0%
0$
#1215000
b1101100 !
b1101100 1
1'
b1 .
0*
b0 +
0/
1-
1%
#1220000
0%
0#
b11100 3
#1225000
00
0,
0'
b11 .
1)
b1 +
b1101101 !
b1101101 1
1%
#1230000
0%
1$
#1235000
b1101110 !
b1101110 1
1(
b10 .
0)
b11 +
1/
0-
1%
#1240000
0%
1#
#1245000
10
1,
0(
b0 .
1*
b10 +
b1101111 !
b1101111 1
1%
#1250000
0%
0$
#1255000
b1110000 !
b1110000 1
1'
b1 .
0*
b0 +
0/
1-
1%
#1260000
0%
0#
b11101 3
#1265000
00
0,
0'
b11 .
1)
b1 +
b1110001 !
b1110001 1
1%
#1270000
0%
1$
#1275000
b1110010 !
b1110010 1
1(
b10 .
0)
b11 +
1/
0-
1%
#1280000
0%
1#
#1285000
10
1,
0(
b0 .
1*
b10 +
b1110011 !
b1110011 1
1%
#1290000
0%
0$
#1295000
b1110100 !
b1110100 1
1'
b1 .
0*
b0 +
0/
1-
1%
#1300000
0%
0#
b11110 3
#1305000
00
0,
0'
b11 .
1)
b1 +
b1110101 !
b1110101 1
1%
#1310000
0%
1$
#1315000
b1110110 !
b1110110 1
1(
b10 .
0)
b11 +
1/
0-
1%
#1320000
0%
1#
#1325000
10
1,
0(
b0 .
1*
b10 +
b1110111 !
b1110111 1
1%
#1330000
0%
0$
#1335000
b1111000 !
b1111000 1
1'
b1 .
0*
b0 +
0/
1-
1%
#1340000
0%
0#
b11111 3
#1345000
00
0,
0'
b11 .
1)
b1 +
b1111001 !
b1111001 1
1%
#1350000
0%
1$
#1355000
b1111010 !
b1111010 1
1(
b10 .
0)
b11 +
1/
0-
1%
#1360000
0%
1#
#1365000
10
1,
0(
b0 .
1*
b10 +
b1111011 !
b1111011 1
1%
#1370000
0%
0$
#1375000
b1111100 !
b1111100 1
1'
b1 .
0*
b0 +
0/
1-
1%
#1380000
0%
0#
b100000 3
#1385000
00
0,
0'
b11 .
1)
b1 +
b1111101 !
b1111101 1
1%
#1390000
0%
1$
#1395000
b1111110 !
b1111110 1
1(
b10 .
0)
b11 +
1/
0-
1%
#1400000
0%
1#
#1405000
10
1,
0(
b0 .
1*
b10 +
b1111111 !
b1111111 1
1%
#1410000
0%
0$
#1415000
b10000000 !
b10000000 1
1'
b1 .
0*
b0 +
0/
1-
1%
#1420000
0%
0#
b100001 3
#1425000
00
0,
0'
b11 .
1)
b1 +
b10000001 !
b10000001 1
1%
#1430000
0%
1$
#1435000
b10000010 !
b10000010 1
1(
b10 .
0)
b11 +
1/
0-
1%
#1440000
0%
1#
#1445000
10
1,
0(
b0 .
1*
b10 +
b10000011 !
b10000011 1
1%
#1450000
0%
0$
#1455000
b10000100 !
b10000100 1
1'
b1 .
0*
b0 +
0/
1-
1%
#1460000
0%
0#
b100010 3
#1465000
00
0,
0'
b11 .
1)
b1 +
b10000101 !
b10000101 1
1%
#1470000
0%
1$
#1475000
b10000110 !
b10000110 1
1(
b10 .
0)
b11 +
1/
0-
1%
#1480000
0%
1#
#1485000
10
1,
0(
b0 .
1*
b10 +
b10000111 !
b10000111 1
1%
#1490000
0%
0$
#1495000
b10001000 !
b10001000 1
1'
b1 .
0*
b0 +
0/
1-
1%
#1500000
0%
0#
b100011 3
#1505000
00
0,
0'
b11 .
1)
b1 +
b10001001 !
b10001001 1
1%
#1510000
0%
1$
#1515000
b10001010 !
b10001010 1
1(
b10 .
0)
b11 +
1/
0-
1%
#1520000
0%
1#
#1525000
10
1,
0(
b0 .
1*
b10 +
b10001011 !
b10001011 1
1%
#1530000
0%
0$
#1535000
b10001100 !
b10001100 1
1'
b1 .
0*
b0 +
0/
1-
1%
#1540000
0%
0#
b100100 3
#1545000
00
0,
0'
b11 .
1)
b1 +
b10001101 !
b10001101 1
1%
#1550000
0%
1$
#1555000
b10001110 !
b10001110 1
1(
b10 .
0)
b11 +
1/
0-
1%
#1560000
0%
1#
#1565000
10
1,
0(
b0 .
1*
b10 +
b10001111 !
b10001111 1
1%
#1570000
0%
0$
#1575000
b10010000 !
b10010000 1
1'
b1 .
0*
b0 +
0/
1-
1%
#1580000
0%
0#
b100101 3
#1585000
00
0,
0'
b11 .
1)
b1 +
b10010001 !
b10010001 1
1%
#1590000
0%
1$
#1595000
b10010010 !
b10010010 1
1(
b10 .
0)
b11 +
1/
0-
1%
#1600000
0%
1#
#1605000
10
1,
0(
b0 .
1*
b10 +
b10010011 !
b10010011 1
1%
#1610000
0%
0$
#1615000
b10010100 !
b10010100 1
1'
b1 .
0*
b0 +
0/
1-
1%
#1620000
0%
0#
b100110 3
#1625000
00
0,
0'
b11 .
1)
b1 +
b10010101 !
b10010101 1
1%
#1630000
0%
1$
#1635000
b10010110 !
b10010110 1
1(
b10 .
0)
b11 +
1/
0-
1%
#1640000
0%
1#
#1645000
10
1,
0(
b0 .
1*
b10 +
b10010111 !
b10010111 1
1%
#1650000
0%
0$
#1655000
b10011000 !
b10011000 1
1'
b1 .
0*
b0 +
0/
1-
1%
#1660000
0%
0#
b100111 3
#1665000
00
0,
0'
b11 .
1)
b1 +
b10011001 !
b10011001 1
1%
#1670000
0%
1$
#1675000
b10011010 !
b10011010 1
1(
b10 .
0)
b11 +
1/
0-
1%
#1680000
0%
1#
#1685000
10
1,
0(
b0 .
1*
b10 +
b10011011 !
b10011011 1
1%
#1690000
0%
0$
#1695000
b10011100 !
b10011100 1
1'
b1 .
0*
b0 +
0/
1-
1%
#1700000
0%
0#
b101000 3
#1705000
00
0,
0'
b11 .
1)
b1 +
b10011101 !
b10011101 1
1%
#1710000
0%
1$
#1715000
b10011110 !
b10011110 1
1(
b10 .
0)
b11 +
1/
0-
1%
#1720000
0%
1#
#1725000
10
1,
0(
b0 .
1*
b10 +
b10011111 !
b10011111 1
1%
#1730000
0%
0$
#1735000
b10100000 !
b10100000 1
1'
b1 .
0*
b0 +
0/
1-
1%
#1740000
0%
0#
b101001 3
#1745000
00
0,
0'
b11 .
1)
b1 +
b10100001 !
b10100001 1
1%
#1750000
0%
1$
#1755000
b10100010 !
b10100010 1
1(
b10 .
0)
b11 +
1/
0-
1%
#1760000
0%
1#
#1765000
10
1,
0(
b0 .
1*
b10 +
b10100011 !
b10100011 1
1%
#1770000
0%
0$
#1775000
b10100100 !
b10100100 1
1'
b1 .
0*
b0 +
0/
1-
1%
#1780000
0%
0#
b101010 3
#1785000
00
0,
0'
b11 .
1)
b1 +
b10100101 !
b10100101 1
1%
#1790000
0%
1$
#1795000
b10100110 !
b10100110 1
1(
b10 .
0)
b11 +
1/
0-
1%
#1800000
0%
1#
#1805000
10
1,
0(
b0 .
1*
b10 +
b10100111 !
b10100111 1
1%
#1810000
0%
0$
#1815000
b10101000 !
b10101000 1
1'
b1 .
0*
b0 +
0/
1-
1%
#1820000
0%
0#
b101011 3
#1825000
00
0,
0'
b11 .
1)
b1 +
b10101001 !
b10101001 1
1%
#1830000
0%
1$
#1835000
b10101010 !
b10101010 1
1(
b10 .
0)
b11 +
1/
0-
1%
#1840000
0%
1#
#1845000
10
1,
0(
b0 .
1*
b10 +
b10101011 !
b10101011 1
1%
#1850000
0%
0$
#1855000
b10101100 !
b10101100 1
1'
b1 .
0*
b0 +
0/
1-
1%
#1860000
0%
0#
b101100 3
#1865000
00
0,
0'
b11 .
1)
b1 +
b10101101 !
b10101101 1
1%
#1870000
0%
1$
#1875000
b10101110 !
b10101110 1
1(
b10 .
0)
b11 +
1/
0-
1%
#1880000
0%
1#
#1885000
10
1,
0(
b0 .
1*
b10 +
b10101111 !
b10101111 1
1%
#1890000
0%
0$
#1895000
b10110000 !
b10110000 1
1'
b1 .
0*
b0 +
0/
1-
1%
#1900000
0%
0#
b101101 3
#1905000
00
0,
0'
b11 .
1)
b1 +
b10110001 !
b10110001 1
1%
#1910000
0%
1$
#1915000
b10110010 !
b10110010 1
1(
b10 .
0)
b11 +
1/
0-
1%
#1920000
0%
1#
#1925000
10
1,
0(
b0 .
1*
b10 +
b10110011 !
b10110011 1
1%
#1930000
0%
0$
#1935000
b10110100 !
b10110100 1
1'
b1 .
0*
b0 +
0/
1-
1%
#1940000
0%
0#
b101110 3
#1945000
00
0,
0'
b11 .
1)
b1 +
b10110101 !
b10110101 1
1%
#1950000
0%
1$
#1955000
b10110110 !
b10110110 1
1(
b10 .
0)
b11 +
1/
0-
1%
#1960000
0%
1#
#1965000
10
1,
0(
b0 .
1*
b10 +
b10110111 !
b10110111 1
1%
#1970000
0%
0$
#1975000
b10111000 !
b10111000 1
1'
b1 .
0*
b0 +
0/
1-
1%
#1980000
0%
0#
b101111 3
#1985000
00
0,
0'
b11 .
1)
b1 +
b10111001 !
b10111001 1
1%
#1990000
0%
1$
#1995000
b10111010 !
b10111010 1
1(
b10 .
0)
b11 +
1/
0-
1%
#2000000
0%
1#
#2005000
10
1,
0(
b0 .
1*
b10 +
b10111011 !
b10111011 1
1%
#2010000
0%
0$
#2015000
b10111100 !
b10111100 1
1'
b1 .
0*
b0 +
0/
1-
1%
#2020000
0%
0#
b110000 3
#2025000
00
0,
0'
b11 .
1)
b1 +
b10111101 !
b10111101 1
1%
#2030000
0%
1$
#2035000
b10111110 !
b10111110 1
1(
b10 .
0)
b11 +
1/
0-
1%
#2040000
0%
1#
#2045000
10
1,
0(
b0 .
1*
b10 +
b10111111 !
b10111111 1
1%
#2050000
0%
0$
#2055000
b11000000 !
b11000000 1
1'
b1 .
0*
b0 +
0/
1-
1%
#2060000
0%
0#
b110001 3
#2065000
00
0,
0'
b11 .
1)
b1 +
b11000001 !
b11000001 1
1%
#2070000
0%
1$
#2075000
b11000010 !
b11000010 1
1(
b10 .
0)
b11 +
1/
0-
1%
#2080000
0%
1#
#2085000
10
1,
0(
b0 .
1*
b10 +
b11000011 !
b11000011 1
1%
#2090000
0%
0$
#2095000
b11000100 !
b11000100 1
1'
b1 .
0*
b0 +
0/
1-
1%
#2100000
0%
0#
b110010 3
#2105000
00
0,
0'
b11 .
1)
b1 +
b11000101 !
b11000101 1
1%
#2110000
0%
1$
#2115000
b11000110 !
b11000110 1
1(
b10 .
0)
b11 +
1/
0-
1%
#2120000
0%
1#
#2125000
10
1,
0(
b0 .
1*
b10 +
b11000111 !
b11000111 1
1%
#2130000
0%
0$
#2135000
b11001000 !
b11001000 1
1'
b1 .
0*
b0 +
0/
1-
1%
#2140000
0%
0#
b110011 3
#2145000
00
0,
0'
b11 .
1)
b1 +
b11001001 !
b11001001 1
1%
#2150000
0%
1$
#2155000
b11001010 !
b11001010 1
1(
b10 .
0)
b11 +
1/
0-
1%
#2160000
0%
1#
#2165000
10
1,
0(
b0 .
1*
b10 +
b11001011 !
b11001011 1
1%
#2170000
0%
0$
#2175000
b11001100 !
b11001100 1
1'
b1 .
0*
b0 +
0/
1-
1%
#2180000
0%
0#
b110100 3
#2185000
00
0,
0'
b11 .
1)
b1 +
b11001101 !
b11001101 1
1%
#2190000
0%
1$
#2195000
b11001110 !
b11001110 1
1(
b10 .
0)
b11 +
1/
0-
1%
#2200000
0%
1#
#2205000
10
1,
0(
b0 .
1*
b10 +
b11001111 !
b11001111 1
1%
#2210000
0%
0$
#2215000
b11010000 !
b11010000 1
1'
b1 .
0*
b0 +
0/
1-
1%
#2220000
0%
0#
b110101 3
#2225000
00
0,
0'
b11 .
1)
b1 +
b11010001 !
b11010001 1
1%
#2230000
0%
1$
#2235000
b11010010 !
b11010010 1
1(
b10 .
0)
b11 +
1/
0-
1%
#2240000
0%
1#
#2245000
10
1,
0(
b0 .
1*
b10 +
b11010011 !
b11010011 1
1%
#2250000
0%
0$
#2255000
b11010100 !
b11010100 1
1'
b1 .
0*
b0 +
0/
1-
1%
#2260000
0%
0#
b110110 3
#2265000
00
0,
0'
b11 .
1)
b1 +
b11010101 !
b11010101 1
1%
#2270000
0%
1$
#2275000
b11010110 !
b11010110 1
1(
b10 .
0)
b11 +
1/
0-
1%
#2280000
0%
1#
#2285000
10
1,
0(
b0 .
1*
b10 +
b11010111 !
b11010111 1
1%
#2290000
0%
0$
#2295000
b11011000 !
b11011000 1
1'
b1 .
0*
b0 +
0/
1-
1%
#2300000
0%
0#
b110111 3
#2305000
00
0,
0'
b11 .
1)
b1 +
b11011001 !
b11011001 1
1%
#2310000
0%
1$
#2315000
b11011010 !
b11011010 1
1(
b10 .
0)
b11 +
1/
0-
1%
#2320000
0%
1#
#2325000
10
1,
0(
b0 .
1*
b10 +
b11011011 !
b11011011 1
1%
#2330000
0%
0$
#2335000
b11011100 !
b11011100 1
1'
b1 .
0*
b0 +
0/
1-
1%
#2340000
0%
0#
b111000 3
#2345000
00
0,
0'
b11 .
1)
b1 +
b11011101 !
b11011101 1
1%
#2350000
0%
1$
#2355000
b11011110 !
b11011110 1
1(
b10 .
0)
b11 +
1/
0-
1%
#2360000
0%
1#
#2365000
10
1,
0(
b0 .
1*
b10 +
b11011111 !
b11011111 1
1%
#2370000
0%
0$
#2375000
b11100000 !
b11100000 1
1'
b1 .
0*
b0 +
0/
1-
1%
#2380000
0%
0#
b111001 3
#2385000
00
0,
0'
b11 .
1)
b1 +
b11100001 !
b11100001 1
1%
#2390000
0%
1$
#2395000
b11100010 !
b11100010 1
1(
b10 .
0)
b11 +
1/
0-
1%
#2400000
0%
1#
#2405000
10
1,
0(
b0 .
1*
b10 +
b11100011 !
b11100011 1
1%
#2410000
0%
0$
#2415000
b11100100 !
b11100100 1
1'
b1 .
0*
b0 +
0/
1-
1%
#2420000
0%
0#
b111010 3
#2425000
00
0,
0'
b11 .
1)
b1 +
b11100101 !
b11100101 1
1%
#2430000
0%
1$
